Workbook

Sheet Sales Entry
A1: SALES ENTRY FORM — Investment Casting Quotation
A2: Sr | B2: Field | C2: Enter Value | D2: Hint / Example
A3: SECTION 1: Part Identification
A4: 1 | B4: Item Code | C4: 30D | D4: e.g. 30D
A5: 2 | B5: Die Code | C5: 30D | D5: same as Item Code usually
A6: 3 | B6: Plant | C6: Nasik | D6: Nasik / Mn
A7: 4 | B7: Date | C7: 16.09.2024 | D7: DD.MM.YYYY
A8: 5 | B8: Quotation No | C8: - | D8: Sales ref number
A9: 6 | B9: Customer Type | C9: Existing | D9: Existing / Prospective
A10: 7 | B10: Dom/Exp | C10: Domestic | D10: Domestic / Export
A11: 8 | B11: Customer Name | C11: DISCOM | D11: Full customer name
A12: 9 | B12: Supply Condition | C12: Machined | D12: Machined / UnMachined / Semi Finished
A13: 10 | B13: Part Description | C13: Down pipe Inlet casting | D13: As per drawing
A14: 11 | B14: Material Type | C14: MS | D14: MS / SS / Aluminium / Copper
A15: 12 | B15: Drw No | C15: 82909101 | D15: Drawing number
... A17: 14 | B17: UOM | C17: Nos | D17: Unit of Measure
A18: 15 | B18: Batch Qty | C18: 250000 | D18: Annual estimated qty
A19: SECTION 2: Composition — Min Values
A20: 1 | B20: Min C | C20: 0.25 | D20: Min % for C
A21: 2 | B21: Min Si | C21: 0.2 | D21: Min % for Si
A22: 3 | B22: Min Mn | C22: 0.7 | D22: Min % for Mn
A23: 4 | B23: Min P | C23: 0 | D23: Min % for P
A24: 5 | B24: Min S | C24: 0 | D24: Min % for S
A25: 6 | B25: Min Cr | C25: 0 | D25: Min % for Cr
A26: 7 | B26: Min Mo | C26: 0 | D26: Min % for Mo
A27: 8 | B27: Min Ni | C27: 0 | D27: Min % for Ni
A28: 9 | B28: Min Ti | C28: 0 | D28: Min % for Ti
A29: SECTION 2: Composition — Max Values
A30: 1 | B30: Max C | C30: 0.35 | D30: Max % for C
A31: 2 | B31: Max Si | C31: 1 | D31: Max % for Si
A32: 3 | B32: Max Mn | C32: 1 | D32: Max % for Mn
A33: 4 | B33: Max P | C33: 0.045 | D33: Max % for P
A34: 5 | B34: Max S | C34: 0.045 | D34: Max % for S
A35: 6 | B35: Max Cr | C35: 0.5 | D35: Max % for Cr
A36: 7 | B36: Max Mo | C36: 0.25 | D36: Max % for Mo
A37: 8 | B37: Max Ni | C37: 0.5 | D37: Max % for Ni
A38: 9 | B38: Max Ti | C38: 0 | D38: Max % for Ti
A39: SECTION 3: Mechanical Properties — Min
A40: 1 | B40: Min UTS | D40: Min value or blank
A41: 2 | B41: Min 0.2% PS/YS | D41: Min value or blank
A42: 3 | B42: Min % Elong | D42: Min value or blank
A43: 4 | B43: Min Impact | D43: Min value or blank
A44: 5 | B44: Min R.A. | D44: Min value or blank
A45: 6 | B45: Min Angle Of Bend | D45: Min value or blank
A46: SECTION 3: Mechanical Properties — Max
A47: 1 | B47: Max UTS | D47: Max value or blank
A48: 2 | B48: Max 0.2% PS/YS | D48: Max value or blank
A49: 3 | B49: Max % Elong | D49: Max value or blank
A50: 4 | B50: Max Impact | D50: Max value or blank
A51: 5 | B51: Max R.A. | D51: Max value or blank
A52: 6 | B52: Max Angle Of Bend | D52: Max value or blank
A53: SECTION 4: Heat Treatment, Surface & Inspection
A54: 1 | B54: Heat Treatment | C54: Quenched & Tempered | D54: From Drop Downs list
A55: 2 | B55: Surface Treatment | C55: Oiling | D55: From Drop Downs list
A56: 3 | B56: Hardness | D56: BHN/HRC value if applicable
A57: 4 | B57: Additional HT | D57: From Drop Downs list
A58: 5 | B58: Inspection | C58: UDL | D58: UDL / Third Party / Outsource
A59: 6 | B59: Additional Hardness | D59: If applicable
A60: SECTION 5: Mould & Yield Parameters
A61: 1 | B61: No / Mould | C61: 10 | D61: Components per mould
A62: 2 | B62: Riser Type | C62: 1X117 MOD | D62: From Drop Downs list
A63: 3 | B63: Component Wax Wt (kg) | C63: 0.104 | D63: Wax wt of 1 component
A64: 4 | B64: Component Metal Wt (kg) | C64: 0.78 | D64: Metal wt of 1 component
A65: 5 | B65: Riser Metal Wt (Manual) | C65: 16 | D65: Enter actual riser metal wt
A66: SECTION 6: Pricing & Targets
A67: 1 | B67: Target Price (₹/Pc) | C67: 900 | D67: Customer's target price
A68: 2 | B68: Currency | C68: INR | D68: INR / USD / GBP / EUR
A69: SECTION 7: Tooling & Development Costs (₹)
A70: 1 | B70: Main Die | C70: 150000 | D70: Main wax injection die cost
A71: 2 | B71: Cavities | C71: 1 cavities | D71: Number of cavities in die
A72: 3 | B72: Setting Fix/Coining | C72: 50000 | D72: Setting fixture cost
A73: 4 | B73: Riser & Feed Die | C73: 0 | D73: 0 if not applicable
A74: 5 | B74: Ceramic Core Die | C74: 0 | D74: 0 if not applicable
A75: 6 | B75: Machining Fixture | C75: 100000 | D75: Machining fixture cost
A76: 7 | B76: Machining Gauges | C76: 80000 | D76: Gauges cost
A77: 8 | B77: Special Tooling | C77: 50000 | D77: Any special tooling

Sheet Estimation Sheet
A1: Estimation
A2: Item Code | B2: ='Sales Entry'!C4 -> 30D | C2: Die Code | D2: ='Sales Entry'!C5 -> 30D | E2: Plant | F2: ='Sales Entry'!C6 -> Nasik | G2: Date : | H2: ='Sales Entry'!C7 -> 16.09.2024
A3: Quotation No | B3: ='Sales Entry'!C8 -> - | C3: Customer Type | D3: ='Sales Entry'!C9 -> Existing | E3: Dom/Exp | F3: ='Sales Entry'!C10 -> Domestic
A4: Customer Name | B4: ='Sales Entry'!C11 -> DISCOM | E4: Supply Condition | F4: ='Sales Entry'!C12 -> Machined
A5: Part Description | B5: ='Sales Entry'!C13 -> Down pipe Inlet casting | E5: Material Type | F5: ='Sales Entry'!C14 -> MS
A6: Drw No | B6: ='Sales Entry'!C15 -> 82909101 | E6: Material | F6: ='Sales Entry'!C16 -> ASTM A 732 2Q
A7: Part No | E7: UOM | F7: ='Sales Entry'!C17 -> Nos | G7: Batch Qty | H7: ='Sales Entry'!C18 -> 250000
A9: Composition
A10: Elements | B10: C | C10: Si | D10: Mn | E10: P | F10: S | G10: Cr | H10: Mo | I10: Ni | J10: Ti | K10: Cu
A11: Min | B11: ='Sales Entry'!C20 -> 0.25 | C11: ='Sales Entry'!C21 -> 0.2 | D11: ='Sales Entry'!C22 -> 0.7 | E11: ='Sales Entry'!C23 -> 0 | F11: ='Sales Entry'!C24 -> 0 | G11: ='Sales Entry'!C25 -> 0 | H11: ='Sales Entry'!C26 -> 0 | I11: ='Sales Entry'!C27 -> 0 | J11: ='Sales Entry'!C28 -> 0
A12: Max | B12: ='Sales Entry'!C30 -> 0.35 | C12: ='Sales Entry'!C31 -> 1 | D12: ='Sales Entry'!C32 -> 1 | E12: ='Sales Entry'!C33 -> 0.045 | F12: ='Sales Entry'!C34 -> 0.045 | G12: ='Sales Entry'!C35 -> 0.5 | H12: ='Sales Entry'!C36 -> 0.25 | I12: ='Sales Entry'!C37 -> 0.5 | J12: ='Sales Entry'!C38 -> 0
A13: Avg | B13: =IFERROR(AVERAGE(B11,B12),"") -> 0.3 | C13: =IFERROR(AVERAGE(C11,C12),"") -> 0.6 | D13: =IFERROR(AVERAGE(D11,D12),"") -> 0.85 | E13: =IFERROR(AVERAGE(E11,E12),"") -> 0.0225 | F13: =IFERROR(AVERAGE(F11,F12),"") -> 0.0225 | G13: =IFERROR(AVERAGE(G11,G12),"") -> 0.25 | H13: =IFERROR(AVERAGE(H11,H12),"") -> 0.125 | I13: =IFERROR(AVERAGE(I11,I12),"") -> 0.25 | J13: =IFERROR(AVERAGE(J11,J12),"") -> 0
A15: Charge Calculation
A16: Virgin Charge | H16: Return Charge
A17: Sr. No. | B17: Code | C17: Metal | D17: Rate | E17: Qty | F17: Value | H17: Sr. No. | I17: Code | J17: Metal | K17: Rate | L17: Qty | M17: Value
A18: 1 | F18: =E18*D18 -> 0 | H18: 1 | J18: Fe Si | K18: 117 | L18: 0.3 | M18: =L18*K18 -> 35.1
A19: 2 | F19: =E19*D19 -> 0 | H19: 6 | J19: Fe Cr 0.3% | K19: 268 | L19: 0.75 | M19: =L19*K19 -> 201
A20: 3 | F20: =E20*D20 -> 0 | H20: 3 | J20: Fe molly | K20: 2900 | L20: 0 | M20: =L20*K20 -> 0
A21: 4 | F21: =E21*D21 -> 0 | H21: 4 | J21: Pu Mn | K21: 177 | L21: 0.8 | M21: =L21*K21 -> 141.6
A22: 5 | F22: =E22*D22 -> 0 | H22: 5 | J22: Pu Ni | K22: 1550 | L22: 0 | M22: =L22*K22 -> 0
A23: 6 | F23: =E23*D23 -> 0 | H23: 6 | J23: Acti. Carbon | K23: 103 | L23: 0.1 | M23: =L23*K23 -> 10.3
A24: 7 | F24: =E24*D24 -> 0 | H24: 7 | J24: FeNb | K24: 3100 | L24: 0 | M24: =L24*K24 -> 0
A25: 8 | F25: =E25*D25 -> 0 | H25: 8 | J25: Nitrided Cr. | K25: 272 | L25: 0 | M25: =L25*K25 -> 0
A26: 9 | F26: =E26*D26 -> 0 | H26: 9 | J26: MSLC | K26: 45 | L26: 53 | M26: =L26*K26 -> 2385
A27: 10 | F27: =E27*D27 -> 0 | H27: 10 | J27: FeTi | K27: 168 | L27: 0 | M27: =L27*K27 -> 0
A28: 11 | F28: =E28*D28 -> 0 | H28: 11 | J28: C24 Return | K28: 56 | L28: 45.05 | M28: =L28*K28 -> 2522.8
A29: 12 | F29: =E29*D29 -> 0 | H29: 12 | M29: =L29*K29 -> 0
A30: Charge Rate (Virgin) | D30: =IFERROR(F30/E30,0) -> 0 | E30: =SUM(E18:E29) -> 0 | F30: =SUM(F18:F29) -> 0 | H30: Charge Rate (Return) | K30: =IFERROR(M30/L30,0) -> 52.958 | L30: =SUM(L18:L29) -> 100 | M30: =SUM(M18:M29) -> 5295.8
A32: Return Calculation | B32: Return Code | C32: Return Alloy Description | D32: Ret Alloy Rate | E32: Charge Rate | F32: Rate To Be considered
E33: =K30 -> 52.958 | F33: =IF(D33=0,E33,D33) -> 52.958
A35: Mechanical Properties
A36: Test | B36: UTS | C36: 0.2% PS/YS | D36: % Elong | E36: Impact | F36: R.A. | G36: Angle Of Bend
A37: Min | B37: ='Sales Entry'!C40 -> 0 | C37: ='Sales Entry'!C41 -> 0 | D37: ='Sales Entry'!C42 -> 0 | E37: ='Sales Entry'!C43 -> 0 | F37: ='Sales Entry'!C44 -> 0 | G37: ='Sales Entry'!C45 -> 0
A38: Max | B38: ='Sales Entry'!C47 -> 0 | C38: ='Sales Entry'!C48 -> 0 | D38: ='Sales Entry'!C49 -> 0 | E38: ='Sales Entry'!C50 -> 0 | F38: ='Sales Entry'!C51 -> 0 | G38: ='Sales Entry'!C52 -> 0
A40: Heat Treatment | B40: ='Sales Entry'!C54 -> Quenched & Tempered | E40: Surface Treatment | F40: ='Sales Entry'!C55 -> Oiling
A41: Hardness | B41: ='Sales Entry'!C56 -> 0
A42: Additional HT | B42: ='Sales Entry'!C57 -> 0 | E42: Inspection | F42: ='Sales Entry'!C58 -> UDL
A43: Additional Hardness | B43: ='Sales Entry'!C59 -> 0
B45: Value | E45: Wax | G45: Metal
A46: Qunatity | B46: =H7 -> 250000 | D46: Specific Gravity | E46: =VLOOKUP(E45,'Drop Downs'!A:B,2,0) -> 1.05 | G46: =VLOOKUP(F5,'Drop Downs'!A:B,2,0) -> 7.86
A47: No / Mould | B47: ='Sales Entry'!C61 -> 10 | D47: Feed Wt. | E47: =G47*$E$46/$G$46 -> 0.01389313 | G47: ='Sales Entry'!C63 -> 0.104
A48: Riser | B48: ='Sales Entry'!C62 -> 1X117 MOD | D48: Componant Wt. | E48: =G48*$E$46/$G$46 -> 0.10419847 | G48: ='Sales Entry'!C64 -> 0.78
A49: Riser Wt. | B49: =VLOOKUP(B48,'Drop Downs'!J:K,2,0) -> 2.405 | C49: =B49*$G$46/$E$46 -> 18.003143 | D49: Comp.+Feed Wt | E49: =E48+E47 -> 0.1180916 | G49: =G48+G47 -> 0.884
A50: Riser Metal Wt (Manual) | B50: ='Sales Entry'!C65 -> 16 | C50: =IF(B50="",C49,B50) -> 16
A51: Yield % | B51: =(G48*B47)/G51 -> 0.31400966 | D51: Mould Wt. | E51: =(E49*B47)+B49 -> 3.585916 | G51: =(G49*B47)+C50 -> 24.84
A53: Rejection | B53: Rej % | C53: Good Castings / Mould | D53: Moulds Required
A54: A | B54: 0.15 | C54: =IF(B54>0,B$47*(1-$B54),"") -> 8.5 | D54: =IFERROR(ROUNDUP(($B$46/$C54),0),"") -> 29412
A55: B | B55: 0.2 | C55: =IF(B55>0,B$47*(1-$B55),"") -> 8 | D55: =IFERROR(ROUNDUP(($B$46/$C55),0),"") -> 31250
A56: C | B56: 0.25 | C56: =IF(B56>0,B$47*(1-$B56),"") -> 7.5 | D56: =IFERROR(ROUNDUP(($B$46/$C56),0),"") -> 33334
A58: Tests To be Performed | B58: Applicable | C58: Sample % | D58: Bulk % | E58: Rate | F58: Amount per PC | G58: Remark
A59: Chemical Analysis | B59: Yes | C59: 1 | D59: 1 | F59: =$E59/(300/($G$51/$B$47)) -> 0
A60: Tensile Test | B60: Yes | C60: 1 | D60: 1 | F60: =$E60/(300/($G$51/$B$47)) -> 0
A61: Impact Test | B61: No | F61: =$E61/(300/($G$51/$B$47)) -> 0
A62: Bend Test | B62: No | F62: =$E62/(300/($G$51/$B$47)) -> 0
A63: Metallography | B63: No | F63: =$E63/(300/($G$51/$B$47)) -> 0
A64: IGCT | B64: Yes | E64: 0 | F64: =$E64/(300/($G$51/$B$47)) -> 0
A65: LP/DP | B65: No | F65: =$E65/(300/($G$51/$B$47)) -> 0
A66: Magnetic Particle | B66: No | F66: =$E66/(300/($G$51/$B$47)) -> 0
A67: Radiography | B67: No | E67: 0 | F67: =$E67/(300/($G$51/$B$47)) -> 0
A68: Any other | B68: No | F68: =$E68/(300/($G$51/$B$47)) -> 0
C70: Weight | D70: Rate | E70: Value With Riser Cr | F70: Value W/o Riser Cr
A71: Wax Cost | B71: Pattern Wax | C71: =E49*B47 -> 1.180916 | D71: =IF($F$2="Nasik",VLOOKUP('Estimation Sheet'!$B71,'Wax Shell Rate'!$A:$D,2,0),IF($F$2="Mn",VLOOKUP('Estimation Sheet'!$B71,'Wax Shell Rate'!$A:$D,3,0),0)) -> 81.79 | E71: =$D71*$C71 -> 96.587122 | F71: =$D71*$C71 -> 96.587122
B72: Riser Wax | C72: =IF(B50="",B49,B50/G46) -> 2.0356234 | D72: =IF($F$2="Nasik",VLOOKUP('Estimation Sheet'!$B72,'Wax Shell Rate'!$A:$D,2,0),IF($F$2="Mn",VLOOKUP('Estimation Sheet'!$B72,'Wax Shell Rate'!$A:$D,3,0),0)) -> 13.88 | E72: =$D72*$C72 -> 28.254453 | F72: =$D72*$C72 -> 28.254453
B73: Water Sol Wax | C73: 0 | D73: =IF($F$2="Nasik",VLOOKUP('Estimation Sheet'!$B73,'Wax Shell Rate'!$A:$D,2,0),IF($F$2="Mn",VLOOKUP('Estimation Sheet'!$B73,'Wax Shell Rate'!$A:$D,3,0),0)) -> 70 | E73: =$D73*$C73 -> 0 | F73: =$D73*$C73 -> 0
B74: Ceramic Core | C74: 0.15 | D74: =IF($F$2="Nasik",VLOOKUP('Estimation Sheet'!$B74,'Wax Shell Rate'!$A:$D,2,0),IF($F$2="Mn",VLOOKUP('Estimation Sheet'!$B74,'Wax Shell Rate'!$A:$D,3,0),0)) -> 400 | E74: =$D74*$C74 -> 60 | F74: =$D74*$C74 -> 60
A75: Shell | B75: Shell Cost | C75: =G51*0.6 -> 14.904 | D75: =IF($F$2="Nasik",IF(F5="MS",VLOOKUP('Estimation Sheet'!$B75,'Wax Shell Rate'!$A:$D,2,0),VLOOKUP('Estimation Sheet'!$B75,'Wax Shell Rate'!$A:$D,3,0)),IF($F$2="Mn",VLOOKUP('Estimation Sheet'!$B75,'Wax Shell Rate'!$A:$D,4,0),0)) -> 42 | E75: =$D75*$C75 -> 625.968 | F75: =$D75*$C75 -> 625.968
A76: Metal Cost | B76: Return
A77: Metal Cost | B77: Mould Wt | C77: =G51 -> 24.84 | D77: =IF(B76="Virgin",D30,K30)*(1+IF(F2="Nasik",Master!C11,Master!B11)) -> 52.958 | F77: =D77*C77 -> 1315.4767
B78: Return Wt | C78: =($G$51*(1-IF($F$2="Nasik",Master!$C$9,Master!$B$9)))-($G$47*$B$47*0.33)-($G$48*$B$47) -> 15.9516 | D78: =IF(E33<>0,E33,IF(B76="Virgin",D30,K30)) -> 52.958 | E78: =($C$77*$D$77)-($D$78*$C$78) -> 470.71189
A79: Consumables | D79: =IF($F$2="Nasik",IF($F$5="SS",VLOOKUP('Estimation Sheet'!$A79,Master!$A:$D,4,0),VLOOKUP('Estimation Sheet'!$A79,Master!$A:$D,3,0)),IF($F$2="Mn",VLOOKUP('Estimation Sheet'!$A79,Master!$A:$D,2,0),0)) -> 645.02 | E79: =$D79*$C$77/VLOOKUP($F$2,Master!$H:$I,2,0) -> 593.4184 | F79: =$D79*$C$77/VLOOKUP($F$2,Master!$H:$I,2,0) -> 593.4184
A80: Heat Treatment | C80: =G48*B47 -> 7.8 | D80: 30 | E80: =$D80*$C80 -> 234 | F80: =$D80*$C80 -> 234
A81: Power | D81: =IF($F$2="Nasik",VLOOKUP('Estimation Sheet'!$A81,Master!$A:$D,3,0),IF($F$2="Mn",VLOOKUP('Estimation Sheet'!$A81,Master!$A:$D,2,0),0)) -> 26 | E81: =$D81*$C$77 -> 645.84 | F81: =$D81*$C$77 -> 645.84
A82: Fuel | D82: =IF($F$2="Nasik",VLOOKUP('Estimation Sheet'!$A82,Master!$A:$D,3,0),IF($F$2="Mn",VLOOKUP('Estimation Sheet'!$A82,Master!$A:$D,2,0),0)) -> 0 | E82: =$D82*$C$77/VLOOKUP($F$2,Master!$H:$I,2,0) -> 0 | F82: =$D82*$C$77/VLOOKUP($F$2,Master!$H:$I,2,0) -> 0
A83: Labour | D83: =IF($F$2="Nasik",VLOOKUP('Estimation Sheet'!$A83,Master!$A:$D,3,0),IF($F$2="Mn",VLOOKUP('Estimation Sheet'!$A83,Master!$A:$D,2,0),0)) -> 488 | E83: =$D83*$C$77/VLOOKUP($F$2,Master!$H:$I,2,0) -> 448.96 | F83: =$D83*$C$77/VLOOKUP($F$2,Master!$H:$I,2,0) -> 448.96
A84: Overhead | D84: =IF($F$2="Nasik",IF($F$5="SS",VLOOKUP('Estimation Sheet'!$A84,Master!$A:$D,4,0),VLOOKUP('Estimation Sheet'!$A84,Master!$A:$D,3,0)),IF($F$2="Mn",VLOOKUP('Estimation Sheet'!$A84,Master!$A:$D,2,0),0)) -> 1621.88 | E84: =$D84*$C$77/VLOOKUP($F$2,Master!$H:$I,2,0) -> 1492.1296 | F84: =$D84*$C$77/VLOOKUP($F$2,Master!$H:$I,2,0) -> 1492.1296
A85: Leak mould Cost | D85: 0.01 | E85: {=SUM(E71:E84*D85)} -> 46.958695 | F85: {=SUM(F71:F84*D85)} -> 55.406343
A86: Total Cost | E86: =SUM(E71:E85) -> 4742.8282 | F86: =SUM(F71:F85) -> 5596.0406
A87: Total Mould Cost | E87: =E86 -> 4742.8282 | F87: =F86 -> 5596.0406
A89: Post Foundry Calculation | B89: Rate | C89: With Riser Cr. | F89: Without Riser Cr. | I89: IH/OS Selection | J89: Cycle Time in Minutes | K89: IH Cost | L89: OS Rate | M89: UOM for Rate
A90: Rejection % | C90: =$B$54 -> 0.15 | D90: =IF($B$55>0,$B$55,"") -> 0.2 | E90: =$B$56 -> 0.25 | F90: =$B$54 -> 0.15 | G90: =$B$55 -> 0.2 | H90: =$B$56 -> 0.25
A91: RC Casting Cost | C91: =IF($B$54>0,$E$87/$B$47/(1-C$90),"") -> 557.97978 | D91: =IF($B$55>0,$E$87/$B$47/(1-D$90),"") -> 592.85352 | E91: =IF($B$56>0,$E$87/$B$47/(1-E$90),"") -> 632.37709 | F91: =IF($B$54>0,$F$87/$B$47/(1-F$90),"") -> 658.35772 | G91: =IF($B$55>0,$F$87/$B$47/(1-G$90),"") -> 699.50508 | H91: =IF($B$56>0,$F$87/$B$47/(1-H$90),"") -> 746.13875
A92: Mould Fettling | B92: 200 | C92: =IF($B$54>0,IF($M92="NO",$B92,IF($M92="MD",$B92/$B$47,IF($M92="KG",$B92*$G$48,0))),"") -> 20 | D92: =IF($B$55>0,IF($M92="NO",$B92,IF($M92="MD",$B92/$B$47,IF($M92="KG",$B92*$G$48,0))),"") -> 20 | E92: =IF($B$56>0,IF($M92="NO",$B92,IF($M92="MD",$B92/$B$47,IF($M92="KG",$B92*$G$48,0))),"") -> 20 | F92: =IF($B$54>0,IF($M92="NO",$B92,IF($M92="MD",$B92/$B$47,IF($M92="KG",$B92*$G$48,0))),"") -> 20 | G92: =IF($B$55>0,IF($M92="NO",$B92,IF($M92="MD",$B92/$B$47,IF($M92="KG",$B92*$G$48,0))),"") -> 20 | H92: =IF($B$56>0,IF($M92="NO",$B92,IF($M92="MD",$B92/$B$47,IF($M92="KG",$B92*$G$48,0))),"") -> 20 | I92: OS | M92: MD
A93: Mould Finishing | B93: 200 | C93: =IF($B$54>0,IF($M93="NO",$B93,IF($M93="MD",$B93/$B$47,IF($M93="KG",$B93*$G$48,0))),"") -> 20 | D93: =IF($B$55>0,IF($M93="NO",$B93,IF($M93="MD",$B93/$B$47,IF($M93="KG",$B93*$G$48,0))),"") -> 20 | E93: =IF($B$56>0,IF($M93="NO",$B93,IF($M93="MD",$B93/$B$47,IF($M93="KG",$B93*$G$48,0))),"") -> 20 | F93: =IF($B$54>0,IF($M93="NO",$B93,IF($M93="MD",$B93/$B$47,IF($M93="KG",$B93*$G$48,0))),"") -> 20 | G93: =IF($B$55>0,IF($M93="NO",$B93,IF($M93="MD",$B93/$B$47,IF($M93="KG",$B93*$G$48,0))),"") -> 20 | H93: =IF($B$56>0,IF($M93="NO",$B93,IF($M93="MD",$B93/$B$47,IF($M93="KG",$B93*$G$48,0))),"") -> 20 | I93: OS | M93: MD
A94: casting setting | B94: 10 | C94: =IF($B$54>0,IF($M94="NO",$B94,IF($M94="MD",$B94/$B$47,IF($M94="KG",$B94*$G$48,0))),"") -> 10 | D94: =IF($B$55>0,IF($M94="NO",$B94,IF($M94="MD",$B94/$B$47,IF($M94="KG",$B94*$G$48,0))),"") -> 10 | E94: =IF($B$56>0,IF($M94="NO",$B94,IF($M94="MD",$B94/$B$47,IF($M94="KG",$B94*$G$48,0))),"") -> 10 | F94: =IF($B$54>0,IF($M94="NO",$B94,IF($M94="MD",$B94/$B$47,IF($M94="KG",$B94*$G$48,0))),"") -> 10 | G94: =IF($B$55>0,IF($M94="NO",$B94,IF($M94="MD",$B94/$B$47,IF($M94="KG",$B94*$G$48,0))),"") -> 10 | H94: =IF($B$56>0,IF($M94="NO",$B94,IF($M94="MD",$B94/$B$47,IF($M94="KG",$B94*$G$48,0))),"") -> 10 | I94: OS | M94: No
A95: casting fettling | B95: 5 | C95: =IF($B$54>0,IF($M95="NO",$B95,IF($M95="MD",$B95/$B$47,IF($M95="KG",$B95*$G$48,0))),"") -> 5 | D95: =IF($B$55>0,IF($M95="NO",$B95,IF($M95="MD",$B95/$B$47,IF($M95="KG",$B95*$G$48,0))),"") -> 5 | E95: =IF($B$56>0,IF($M95="NO",$B95,IF($M95="MD",$B95/$B$47,IF($M95="KG",$B95*$G$48,0))),"") -> 5 | F95: =IF($B$54>0,IF($M95="NO",$B95,IF($M95="MD",$B95/$B$47,IF($M95="KG",$B95*$G$48,0))),"") -> 5 | G95: =IF($B$55>0,IF($M95="NO",$B95,IF($M95="MD",$B95/$B$47,IF($M95="KG",$B95*$G$48,0))),"") -> 5 | H95: =IF($B$56>0,IF($M95="NO",$B95,IF($M95="MD",$B95/$B$47,IF($M95="KG",$B95*$G$48,0))),"") -> 5 | I95: OS | M95: =IFERROR(VLOOKUP(A95,'Drop Downs'!Z:AA,2,0),"") -> NO
A96: feed machining | B96: 10 | C96: =IF($B$54>0,IF($M96="NO",$B96,IF($M96="MD",$B96/$B$47,IF($M96="KG",$B96*$G$48,0))),"") -> 10 | D96: =IF($B$55>0,IF($M96="NO",$B96,IF($M96="MD",$B96/$B$47,IF($M96="KG",$B96*$G$48,0))),"") -> 10 | E96: =IF($B$56>0,IF($M96="NO",$B96,IF($M96="MD",$B96/$B$47,IF($M96="KG",$B96*$G$48,0))),"") -> 10 | F96: =IF($B$54>0,IF($M96="NO",$B96,IF($M96="MD",$B96/$B$47,IF($M96="KG",$B96*$G$48,0))),"") -> 10 | G96: =IF($B$55>0,IF($M96="NO",$B96,IF($M96="MD",$B96/$B$47,IF($M96="KG",$B96*$G$48,0))),"") -> 10 | H96: =IF($B$56>0,IF($M96="NO",$B96,IF($M96="MD",$B96/$B$47,IF($M96="KG",$B96*$G$48,0))),"") -> 10 | I96: OS | M96: =IFERROR(VLOOKUP(A96,'Drop Downs'!Z:AA,2,0),"") -> No
A97: Heat punching | B97: 4 | C97: =IF($B$54>0,IF($M97="NO",$B97,IF($M97="MD",$B97/$B$47,IF($M97="KG",$B97*$G$48,0))),"") -> 4 | D97: =IF($B$55>0,IF($M97="NO",$B97,IF($M97="MD",$B97/$B$47,IF($M97="KG",$B97*$G$48,0))),"") -> 4 | E97: =IF($B$56>0,IF($M97="NO",$B97,IF($M97="MD",$B97/$B$47,IF($M97="KG",$B97*$G$48,0))),"") -> 4 | F97: =IF($B$54>0,IF($M97="NO",$B97,IF($M97="MD",$B97/$B$47,IF($M97="KG",$B97*$G$48,0))),"") -> 4 | G97: =IF($B$55>0,IF($M97="NO",$B97,IF($M97="MD",$B97/$B$47,IF($M97="KG",$B97*$G$48,0))),"") -> 4 | H97: =IF($B$56>0,IF($M97="NO",$B97,IF($M97="MD",$B97/$B$47,IF($M97="KG",$B97*$G$48,0))),"") -> 4 | I97: OS | M97: =IFERROR(VLOOKUP(A97,'Drop Downs'!Z:AA,2,0),"") -> NO
C98: =IF($B$54>0,IF($M98="NO",$B98,IF($M98="MD",$B98/$B$47,IF($M98="KG",$B98*$G$48,0))),"") -> 0 | D98: =IF($B$55>0,IF($M98="NO",$B98,IF($M98="MD",$B98/$B$47,IF($M98="KG",$B98*$G$48,0))),"") -> 0 | E98: =IF($B$56>0,IF($M98="NO",$B98,IF($M98="MD",$B98/$B$47,IF($M98="KG",$B98*$G$48,0))),"") -> 0 | F98: =IF($B$54>0,IF($M98="NO",$B98,IF($M98="MD",$B98/$B$47,IF($M98="KG",$B98*$G$48,0))),"") -> 0 | G98: =IF($B$55>0,IF($M98="NO",$B98,IF($M98="MD",$B98/$B$47,IF($M98="KG",$B98*$G$48,0))),"") -> 0 | H98: =IF($B$56>0,IF($M98="NO",$B98,IF($M98="MD",$B98/$B$47,IF($M98="KG",$B98*$G$48,0))),"") -> 0 | I98: IH | M98: =IFERROR(VLOOKUP(A98,'Drop Downs'!Z:AA,2,0),"")
C99: =IF($B$54>0,IF($M99="NO",$B99,IF($M99="MD",$B99/$B$47,IF($M99="KG",$B99*$G$48,0))),"") -> 0 | D99: =IF($B$55>0,IF($M99="NO",$B99,IF($M99="MD",$B99/$B$47,IF($M99="KG",$B99*$G$48,0))),"") -> 0 | E99: =IF($B$56>0,IF($M99="NO",$B99,IF($M99="MD",$B99/$B$47,IF($M99="KG",$B99*$G$48,0))),"") -> 0 | F99: =IF($B$54>0,IF($M99="NO",$B99,IF($M99="MD",$B99/$B$47,IF($M99="KG",$B99*$G$48,0))),"") -> 0 | G99: =IF($B$55>0,IF($M99="NO",$B99,IF($M99="MD",$B99/$B$47,IF($M99="KG",$B99*$G$48,0))),"") -> 0 | H99: =IF($B$56>0,IF($M99="NO",$B99,IF($M99="MD",$B99/$B$47,IF($M99="KG",$B99*$G$48,0))),"") -> 0 | I99: IH | M99: =IFERROR(VLOOKUP(A99,'Drop Downs'!Z:AA,2,0),"")
C100: =IF($B$54>0,IF($M100="NO",$B100,IF($M100="MD",$B100/$B$47,IF($M100="KG",$B100*$G$48,0))),"") -> 0 | D100: =IF($B$55>0,IF($M100="NO",$B100,IF($M100="MD",$B100/$B$47,IF($M100="KG",$B100*$G$48,0))),"") -> 0 | E100: =IF($B$56>0,IF($M100="NO",$B100,IF($M100="MD",$B100/$B$47,IF($M100="KG",$B100*$G$48,0))),"") -> 0 | F100: =IF($B$54>0,IF($M100="NO",$B100,IF($M100="MD",$B100/$B$47,IF($M100="KG",$B100*$G$48,0))),"") -> 0 | G100: =IF($B$55>0,IF($M100="NO",$B100,IF($M100="MD",$B100/$B$47,IF($M100="KG",$B100*$G$48,0))),"") -> 0 | H100: =IF($B$56>0,IF($M100="NO",$B100,IF($M100="MD",$B100/$B$47,IF($M100="KG",$B100*$G$48,0))),"") -> 0 | I100: IH | M100: =IFERROR(VLOOKUP(A100,'Drop Downs'!Z:AA,2,0),"")
C101: =IF($B$54>0,IF($M101="NO",$B101,IF($M101="MD",$B101/$B$47,IF($M101="KG",$B101*$G$48,0))),"") -> 0 | D101: =IF($B$55>0,IF($M101="NO",$B101,IF($M101="MD",$B101/$B$47,IF($M101="KG",$B101*$G$48,0))),"") -> 0 | E101: =IF($B$56>0,IF($M101="NO",$B101,IF($M101="MD",$B101/$B$47,IF($M101="KG",$B101*$G$48,0))),"") -> 0 | F101: =IF($B$54>0,IF($M101="NO",$B101,IF($M101="MD",$B101/$B$47,IF($M101="KG",$B101*$G$48,0))),"") -> 0 | G101: =IF($B$55>0,IF($M101="NO",$B101,IF($M101="MD",$B101/$B$47,IF($M101="KG",$B101*$G$48,0))),"") -> 0 | H101: =IF($B$56>0,IF($M101="NO",$B101,IF($M101="MD",$B101/$B$47,IF($M101="KG",$B101*$G$48,0))),"") -> 0 | I101: IH | M101: =IFERROR(VLOOKUP(A101,'Drop Downs'!Z:AA,2,0),"")
C102: =IF($B$54>0,IF($M102="NO",$B102,IF($M102="MD",$B102/$B$47,IF($M102="KG",$B102*$G$48,0))),"") -> 0 | D102: =IF($B$55>0,IF($M102="NO",$B102,IF($M102="MD",$B102/$B$47,IF($M102="KG",$B102*$G$48,0))),"") -> 0 | E102: =IF($B$56>0,IF($M102="NO",$B102,IF($M102="MD",$B102/$B$47,IF($M102="KG",$B102*$G$48,0))),"") -> 0 | F102: =IF($B$54>0,IF($M102="NO",$B102,IF($M102="MD",$B102/$B$47,IF($M102="KG",$B102*$G$48,0))),"") -> 0 | G102: =IF($B$55>0,IF($M102="NO",$B102,IF($M102="MD",$B102/$B$47,IF($M102="KG",$B102*$G$48,0))),"") -> 0 | H102: =IF($B$56>0,IF($M102="NO",$B102,IF($M102="MD",$B102/$B$47,IF($M102="KG",$B102*$G$48,0))),"") -> 0 | I102: IH | M102: =IFERROR(VLOOKUP(A102,'Drop Downs'!Z:AA,2,0),"")
C103: =IF($B$54>0,IF($M103="NO",$B103,IF($M103="MD",$B103/$B$47,IF($M103="KG",$B103*$G$48,0))),"") -> 0 | D103: =IF($B$55>0,IF($M103="NO",$B103,IF($M103="MD",$B103/$B$47,IF($M103="KG",$B103*$G$48,0))),"") -> 0 | E103: =IF($B$56>0,IF($M103="NO",$B103,IF($M103="MD",$B103/$B$47,IF($M103="KG",$B103*$G$48,0))),"") -> 0 | F103: =IF($B$54>0,IF($M103="NO",$B103,IF($M103="MD",$B103/$B$47,IF($M103="KG",$B103*$G$48,0))),"") -> 0 | G103: =IF($B$55>0,IF($M103="NO",$B103,IF($M103="MD",$B103/$B$47,IF($M103="KG",$B103*$G$48,0))),"") -> 0 | H103: =IF($B$56>0,IF($M103="NO",$B103,IF($M103="MD",$B103/$B$47,IF($M103="KG",$B103*$G$48,0))),"") -> 0 | I103: IH | M103: =IFERROR(VLOOKUP(A103,'Drop Downs'!Z:AA,2,0),"")
C104: =IF($B$54>0,IF($M104="NO",$B104,IF($M104="MD",$B104/$B$47,IF($M104="KG",$B104*$G$48,0))),"") -> 0 | D104: =IF($B$55>0,IF($M104="NO",$B104,IF($M104="MD",$B104/$B$47,IF($M104="KG",$B104*$G$48,0))),"") -> 0 | E104: =IF($B$56>0,IF($M104="NO",$B104,IF($M104="MD",$B104/$B$47,IF($M104="KG",$B104*$G$48,0))),"") -> 0 | F104: =IF($B$54>0,IF($M104="NO",$B104,IF($M104="MD",$B104/$B$47,IF($M104="KG",$B104*$G$48,0))),"") -> 0 | G104: =IF($B$55>0,IF($M104="NO",$B104,IF($M104="MD",$B104/$B$47,IF($M104="KG",$B104*$G$48,0))),"") -> 0 | H104: =IF($B$56>0,IF($M104="NO",$B104,IF($M104="MD",$B104/$B$47,IF($M104="KG",$B104*$G$48,0))),"") -> 0 | I104: IH | M104: =IFERROR(VLOOKUP(A104,'Drop Downs'!Z:AA,2,0),"")
C105: =IF($B$54>0,IF($M105="NO",$B105,IF($M105="MD",$B105/$B$47,IF($M105="KG",$B105*$G$48,0))),"") -> 0 | D105: =IF($B$55>0,IF($M105="NO",$B105,IF($M105="MD",$B105/$B$47,IF($M105="KG",$B105*$G$48,0))),"") -> 0 | E105: =IF($B$56>0,IF($M105="NO",$B105,IF($M105="MD",$B105/$B$47,IF($M105="KG",$B105*$G$48,0))),"") -> 0 | F105: =IF($B$54>0,IF($M105="NO",$B105,IF($M105="MD",$B105/$B$47,IF($M105="KG",$B105*$G$48,0))),"") -> 0 | G105: =IF($B$55>0,IF($M105="NO",$B105,IF($M105="MD",$B105/$B$47,IF($M105="KG",$B105*$G$48,0))),"") -> 0 | H105: =IF($B$56>0,IF($M105="NO",$B105,IF($M105="MD",$B105/$B$47,IF($M105="KG",$B105*$G$48,0))),"") -> 0 | I105: IH | M105: =IFERROR(VLOOKUP(A105,'Drop Downs'!Z:AA,2,0),"")
A106: Commission | C106: =IF($B$54>0,SUM(C91:C105)*$B106,"") -> 0 | D106: =IF($B$55>0,SUM(D91:D105)*$B106,"") -> 0 | E106: =IF($B$56>0,SUM(E91:E105)*$B106,"") -> 0 | F106: =IF($B$54>0,SUM(F91:F105)*$B106,"") -> 0 | G106: =IF($B$55>0,SUM(G91:G105)*$B106,"") -> 0 | H106: =IF($B$56>0,SUM(H91:H105)*$B106,"") -> 0
A107: Sub Total | C107: =SUM(C91:C106) -> 626.97978 | D107: =SUM(D91:D106) -> 661.85352 | E107: =SUM(E91:E106) -> 701.37709 | F107: =SUM(F91:F106) -> 727.35772 | G107: =SUM(G91:G106) -> 768.50508 | H107: =SUM(H91:H106) -> 815.13875
A108: Std Testing Charges | C108: =IF($B$54>0,$B108/(1-C$90),"") -> 0 | D108: =IF($B$54>0,$B108/(1-D$90),"") -> 0 | E108: =IF($B$54>0,$B108/(1-E$90),"") -> 0 | F108: =IF($B$54>0,$B108/(1-F$90),"") -> 0 | G108: =IF($B$54>0,$B108/(1-G$90),"") -> 0 | H108: =IF($B$54>0,$B108/(1-H$90),"") -> 0
A109: Additional Testing Charges | B109: 0 | C109: =IF($B$54>0,$B109,"") -> 0 | D109: =IF($B$55>0,$B109,"") -> 0 | E109: =IF($B$56>0,$B109,"") -> 0 | F109: =IF($B$54>0,$B109,"") -> 0 | G109: =IF($B$55>0,$B109,"") -> 0 | H109: =IF($B$56>0,$B109,"") -> 0
A110: As Cast Cost | C110: =IF($B$54>0,C107+C108+C109,"") -> 626.97978 | D110: =IF($B$55>0,D107+D108+D109,"") -> 661.85352 | E110: =IF($B$56>0,E107+E108+E109,"") -> 701.37709 | F110: =IF($B$54>0,F107+F108+F109,"") -> 727.35772 | G110: =IF($B$55>0,G107+G108+G109,"") -> 768.50508 | H110: =IF($B$56>0,H107+H108+H109,"") -> 815.13875
...

Sheet User Training
A1: USER TRAINING GUIDE — Estimation Template
A3: SECTION A: Getting Started — Workflow Steps
A4: Step 1 | B4: Open 'Sales Entry' sheet | C4: This is the ONLY sheet where you enter customer & part data
A5: Step 2 | B5: Fill all 7 sections in Sales Entry | C5: Item Code → Tooling Costs (69 fields total)
A6: Step 3 | B6: Switch to 'Estimation Sheet' | C6: All linked cells (GREEN) auto-populate from Sales Entry
A7: Step 4 | B7: Fill Charge Metals (Rows 18–28) | C7: Enter alloy metals, rates, quantities directly on Estimation Sheet
A8: Step 5 | B8: Fill Post-Foundry Operations (Rows 89–97) | C8: Enter fettling, finishing, HT, sandblasting rates
A9: Step 6 | B9: Fill Machining Operations (Rows 112–121) | C9: Enter cycle time, machine type, manual addon
A10: Step 7 | B10: Review BLUE formula cells | C10: These auto-calculate — DO NOT EDIT
A11: Step 8 | B11: Check final pricing (Rows 130–140) | C11: Verify Finished Casting Cost, Ex Price, Quoted Sales Price
A12: Step 9 | B12: Review Tooling (Rows 147–154) | C12: Auto-populated from Sales Entry Section 7
A13: Step 10 | B13: Print / Export for customer quotation | C13: Final review before sharing
A15: SECTION B: Color Legend — Estimation Sheet
A16: 🟢 GREEN | B16: Linked from Sales Entry | C16: Auto-filled — DO NOT type here. Edit in Sales Entry.
A17: 🔵 BLUE | B17: Formula / Auto-Calculated | C17: Computed by formulas — NEVER edit these cells.
A18: 🟡 YELLOW | B18: Direct Input on Est Sheet | C18: Enter directly (charge metals, post-foundry, machining).
A19: ⬜ WHITE | B19: Label / Header | C19: Static text — DO NOT modify.
A21: SECTION C: Field-by-Field Guide — Sales Entry (69 Fields)
A22: SECTION 1: Part Identification (15 fields)
B23: Item Code | C23: Unique code for the casting part | D23: Must match Die Code in most cases
B24: Die Code | C24: Wax injection die reference | D24: Used to track tooling
B25: Plant | C25: Manufacturing plant | D25: Nasik or Mn — drives different cost rates
B26: Date | C26: Quotation date | D26: Format: DD.MM.YYYY
B27: Quotation No | C27: Sales reference number | D27: Use '-' if not assigned yet
B28: Customer Type | C28: Existing or Prospective | D28: Affects pricing strategy
B29: Dom/Exp | C29: Domestic or Export | D29: Export uses foreign currency conversion
B30: Customer Name | C30: Full customer name | D30: As per PO / enquiry
B31: Supply Condition | C31: Machined / UnMachined / Semi Finished | D31: Drives machining cost section
B32: Part Description | C32: Part name as per drawing | D32: Be specific
B33: Material Type | C33: MS / SS / Aluminium / Copper | D33: Drives density, shell cost, overheads
B34: Drw No | C34: Drawing number | D34: Customer drawing reference
... B37: Batch Qty | C37: Annual estimated quantity | D37: Drives amortization of tooling
A38: SECTION 2: Composition (18 fields — 9 Min + 9 Max)
B39: Min/Max C, Si, Mn... | C39: Chemical composition range | D39: From material spec / customer drawing
B40: Avg (auto) | C40: Auto-calculated average
A41: SECTION 3: Mechanical Properties (12 fields — 6 Min + 6 Max)
B42: UTS | C42: Ultimate Tensile Strength | D42: In MPa or N/mm²
B43: 0.2% PS/YS | C43: Proof Stress / Yield Strength | D43: In MPa
B44: % Elong | C44: Percentage Elongation | D44: Ductility measure
B45: Impact | C45: Impact value (Charpy) | D45: In Joules
B46: R.A. | C46: Reduction in Area | D46: Percentage
B47: Angle Of Bend | C47: Bend test angle | D47: In degrees
A48: SECTION 4: HT, Surface & Inspection (6 fields)
B49: Heat Treatment | C49: Primary heat treatment | D49: Select from Drop Downs sheet
B50: Surface Treatment | C50: Surface finish requirement | D50: Oiling / Pickling / Passivation etc.
B51: Hardness | C51: Required hardness (BHN/HRC) | D51: Leave blank if not specified
B52: Additional HT | C52: Secondary heat treatment | D52: Induction Hardening / Carburising etc.
B53: Inspection | C53: Inspection method | D53: UDL (in-house) / Third Party / Outsource
B54: Additional Hardness | C54: Secondary hardness spec | D54: Leave blank if not applicable
A55: SECTION 5: Mould & Yield (5 fields)
B56: No / Mould | C56: Components per mould tree | D56: Impacts yield & cost per piece
B57: Riser Type | C57: Riser type used | D57: Select from Drop Downs — drives riser weight
B58: Component Wax Wt | C58: Wax weight per component (kg) | D58: From wax pattern study
B59: Component Metal Wt | C59: Metal weight per component (kg) | D59: =Wax Wt * (Metal Density / Wax Density) -> #NAME?
B60: Riser Metal Wt | C60: Actual riser metal weight (kg) | D60: Override if manual measurement available
A61: SECTION 6: Pricing (2 fields)
B62: Target Price | C62: Customer's target price per piece | D62: In ₹ — for comparison only
B63: Currency | C63: Quotation currency | D63: INR / USD / GBP / EUR
A64: SECTION 7: Tooling (8 fields)
B65: Main Die | C65: Wax injection die cost | D65: ₹ — quoted separately to customer
B66: Cavities | C66: Number of cavities in die | D66: Drives wax injection cycle time
B67: Setting Fix/Coining | C67: Setting / coining fixture cost | D67: ₹
B68: Riser & Feed Die | C68: Riser & feed die cost | D68: ₹ — enter 0 if not applicable
B69: Ceramic Core Die | C69: Ceramic core die cost | D69: ₹ — enter 0 if not applicable
B70: Machining Fixture | C70: Machining fixture cost | D70: ₹
B71: Machining Gauges | C71: Gauges cost | D71: ₹
B72: Special Tooling | C72: Any special tooling | D72: ₹
A74: SECTION D: Do's and Don'ts
B75: ✅ ALWAYS enter data in 'Sales Entry' sheet for the 69 linked fields
B76: ✅ ALWAYS fill all 7 sections before reviewing the Estimation Sheet
B77: ✅ ALWAYS check that Plant (Nasik/Mn) is correct — it drives cost rates from Master
B78: ✅ ALWAYS verify Material Type (MS/SS) — it drives shell cost, density, overheads
B79: ✅ ALWAYS review Avg composition (Row 13) — auto-calculated from Min/Max
B80: ✅ ALWAYS enter Charge Metals, Post-Foundry, and Machining DIRECTLY on Estimation Sheet
B81: ✅ ALWAYS cross-check final price with customer's Target Price (Row 132, Col I)
B82: ✅ ALWAYS verify Tooling Total (Row 154) = Die Total + Machining Total
B83: ✅ USE the Drop Downs sheet for valid values (Material Type, HT, Riser, etc.)
B84: ✅ SAVE a copy before making any structural changes
B85: ❌ NEVER type values into GREEN cells on Estimation Sheet — use Sales Entry
B86: ❌ NEVER edit or delete BLUE formula cells — they contain critical calculations
... B94: ❌ AVOID leaving Batch Qty as 0 — causes #DIV/0! errors in per-piece calculations
A96: SECTION E: Estimation Sheet — Direct Edit Areas
B97: Charge Metals | C97: Location: Rows 18–28 | D97: Enter alloy code, metal name, rate/kg, qty/100kg for Virgin & Return charge
B98: Post-Foundry Ops | C98: Location: Rows 89–97 | D98: Enter operation name, rate, IH/OS flag for fettling, finishing, HT, etc.
B99: Machining Ops | C99: Location: Rows 112–121 | D99: Enter operation, cycle time, machine type, manual addon for each machining step
B100: Testing Charges | C100: Location: Rows 59–68 | D100: Enter sample%, bulk%, rate for each test (Chemical, Tensile, Impact, etc.)
B101: Rejection % | C101: Location: Rows 54–56 | D101: Standard: 15%, 20%, 25% — adjust only if process data supports change
B102: Cost Factors | C102: Location: Row 73–74, 80, 85 | D102: Water-sol wax, ceramic core usage, HT rate, leak test % — plant-specific
B103: Pricing Overrides | C103: Location: Row 127–128, 139 | D103: Machining Rej%, Overhead%, Quoted base — change with approval only
A105: SECTION F: Formula Protection Rules
B106: 363 formula cells | C106: All auto-calc cells on Estimation Sheet | D106: NEVER edit — marked in BLUE
B107: Metal Cost formula | C107: Row 29: Charge Rate = Σ(Rate × Qty) | D107: Drives entire costing — DO NOT touch
B108: Yield Calculations | C108: Rows 50–53: Mould Wt, Yield %, Return Wt | D108: Linked to mould parameters — auto
B109: Cost Build-Up | C109: Rows 70–87: Metal, Wax, Shell, OH, Labour | D109: Multi-scenario (15/20/25% rej) — auto
B110: Post-Foundry Totals | C110: Rows 98–109: Sub-totals, As-Cast Cost | D110: Summation formulas — DO NOT edit
B111: Machining Cost | C111: Rows 126–130: Rej, OH, Total Machining | D111: Drives Finished Casting Cost — auto
B112: Final Pricing | C112: Rows 132–140: Ex Price, Rate/Kg, Quoted | D112: Final output formulas — auto
B113: Dev Cost Total | C113: Row 154: Total Dev Cost | D113: =Die Total + Machining Total — auto -> #NAME?
A115: SECTION G: Troubleshooting Common Issues
B116: #REF! error | C116: Cause: A linked cell reference is broken | D116: Fix: Check Sales Entry sheet name hasn't changed; re-enter the value
...

Sheet Drop Downs
A1: Material Type | B1: Density | C1: Customer Type | D1: Yes/No | E1: Additional HT | F1: Supply Condition | G1: Surface Treatment | H1: Heat Treatment | I1: Inspection | J1: Riser | K1: Riser Weight | L1: Geography | M1: Metal Code | N1: Metal | P1: Mechanical Prop | R1: Plant | S1: IH/OS | U1: Charge Type | W1: Machining Operations | X1: Machine Type | Y1: Machine Category | Z1: Post Foundry Operations | AA1: UOM of Operation
A2: MS | B2: 7.86 | C2: Existing | D2: Yes | E2: Induction Hardening | F2: Machined | G2: Pickling | H2: Annealing | I2: UDL | J2: Star Riser | K2: 4.021 | L2: Domestic | M2: C | N2: Carbon | P2: UTS | R2: Nasik | S2: IH | U2: Virgin | W2: Casting Machining | X2: EC 300 | Y2: HMC | Z2: Mould Fettling | AA2: MD
A3: SS | B3: 7.86 | C3: Prospective | D3: No | E3: Hardening & Tempering | F3: UnMachined | G3: Passivation | H3: Hardening | I3: Third Party | J3: 3V Full | K3: 1.8 | L3: Export | M3: Si | N3: Silicon | P3: 0.2% PS/YS | R3: Mn | S3: OS | U3: Return | W3: Casting Drilling | X3: EC 400 - 1 | Y3: HMC | Z3: Mould Finishing | AA3: MD
A4: Aluminium | B4: 2.7 | E4: Carburising | F4: Semi Finished | G4: Bath Nitrating | H4: Normalising | I4: Outsource | J4: 6T | K4: 1.9 | M4: Cr | N4: Chrome | P4: % Elong | W4: Casting Milling | X4: EC 400 - 2 | Y4: HMC | Z4: Casting Fettling | AA4: NO
A5: Wax | B5: 1.05 | E5: Hardening | G5: Electroplating | H5: Solution Annealing | J5: 5T spl+1 | K5: 1.8 | M5: Mn | N5: Mangenese | P5: Impact | W5: Casting Tapping | X5: VF 2 - 1 | Y5: VMC | Z5: Casting Sandblasting | AA5: NO
A6: Copper | B6: 8.9 | E6: Nitriding | G6: Oiling | H6: Tempering | J6: 5T-spl New | K6: 2.405 | M6: P | N6: Phosperous | P6: R.A. | W6: Casting Deburing | X6: VF 2 - 2 | Y6: VMC | Z6: Casting Rework | AA6: NO
G7: Sand Blast | H7: Case Carburising & Tempering | J7: 26E190 Riser | K7: 2.405 | M7: S | N7: Sulpher | P7: Angle Of Bend | W7: Induction Hardening | X7: VF 2 - 3 | Y7: VMC | Z7: Casting Pickling | AA7: KG
G8: SS.TUMBLAST & OILING | H8: Austempering | J8: 5T SPL Modified | K8: 2.004 | M8: Ni | N8: Nickel | X8: VF 2 - 4 | Y8: VMC | Z8: Casting Passivation | AA8: KG
G9: Pickling & Passivation | H9: Normalising & Tempering | J9: 29N01 | K9: 2.004 | M9: Cu | N9: Copper | X9: VF 2 - 5 | Y9: VMC | Z9: Casting Setting | AA9: NO
H10: Normalising, Case Carburizing & Tempering | J10: 1X117 MOD | K10: 2.405 | M10: Mo | X10: VF 4 - 1 | Y10: VMC | Z10: Casting Heat Treatment | AA10: KG
H11: Solution Annealing, Homogenization & Precipitation Hardening. | J11: V5 | K11: 1.807 | M11: N | X11: MAKINO 01 | Y11: MAKINO | Z11: Casting Induction Hardening | AA11: NO
H12: As cast | J12: Y SHAPE RISER | K12: 2 | M12: Ti | X12: MAKINO 02 | Y12: MAKINO | Z12: Casting Packing
H13: Quenched & Tempered | J13: Star Riser New | K13: 2.335 | X13: MAKINO 03 | Y13: MAKINO | Z13: Feed machining | AA13: No
H14: Normalising, Hardening & Tempering | J14: 8T | K14: 1.4 | X14: LMW 01 | Y14: LMW | Z14: Normalized OS | AA14: KG
J15: New Riser | K15: 1.2 | X15: LMW 02 | Y15: LMW | Z15: Hardening Tempering OS | AA15: KG
J16: 26E59 RISER | K16: 1.7 | X16: ACE SUPER JOBBER | Y16: ACE | Z16: Heat punching | AA16: NO
J17: NA | K17: 0 | X17: ACE JR 300-1 | Y17: ACE | Z17: Feed machining | AA17: No
J18: V5 Long | K18: 1.8 | X18: ACE JR 300-2 | Y18: ACE | Z18: Casting pressure testing | AA18: No
J19: 22F40 MODIFIED | K19: 2.16 | X19: VMC 350 - 1 | Y19: AMS VMC
J20: 7T | K20: 1.3 | X20: VMC 350 - 2 | Y20: AMS VMC
X21: VMC 350 - 3 | Y21: AMS VMC
X22: VMC 400 - 1 | Y22: AMS VMC

Sheet Machine Shop Rates
A2: Machine Name | B2: Machine Type | C2: Machine Description | D2: Labour | E2: Power | F2: Depreciation | G2: Consumables | H2: Maintenance | I2: Maintenance Spares | J2: AMC Cost | K2: Any Other Cost | L2: Total | M2: Total M/c Hours Available | N2: Rate / Hr
A3: EC 300 | B3: HMC | D3: =105*22*26*12 -> 720720 | L3: =SUM(D3:K3) -> 720720 | M3: =22*26*12 -> 6864 | N3: =L3/M3 -> 105 | O3: =M3*N3 -> 720720
A4: EC 400 - 1 | B4: HMC | D4: =105*22*26*12 -> 720720 | L4: =SUM(D4:K4) -> 720720 | M4: =22*26*12 -> 6864 | N4: =L4/M4 -> 105
A5: EC 400 - 2 | B5: HMC | D5: =105*22*26*12 -> 720720 | L5: =SUM(D5:K5) -> 720720 | M5: =22*26*12 -> 6864 | N5: =L5/M5 -> 105
A6: VF 2 - 1 | B6: VMC | D6: =105*22*26*12 -> 720720 | L6: =SUM(D6:K6) -> 720720 | M6: =22*26*12 -> 6864 | N6: =L6/M6 -> 105
A7: VF 2 - 2 | B7: VMC | D7: =105*22*26*12 -> 720720 | L7: =SUM(D7:K7) -> 720720 | M7: =22*26*12 -> 6864 | N7: =L7/M7 -> 105
A8: VF 2 - 3 | B8: VMC | D8: =105*22*26*12 -> 720720 | L8: =SUM(D8:K8) -> 720720 | M8: =22*26*12 -> 6864 | N8: =L8/M8 -> 105
A9: VF 2 - 4 | B9: VMC | D9: =105*22*26*12 -> 720720 | L9: =SUM(D9:K9) -> 720720 | M9: =22*26*12 -> 6864 | N9: =L9/M9 -> 105
A10: VF 2 - 5 | B10: VMC | D10: =105*22*26*12 -> 720720 | L10: =SUM(D10:K10) -> 720720 | M10: =22*26*12 -> 6864 | N10: =L10/M10 -> 105
A11: VF 4 - 1 | B11: VMC | D11: =105*22*26*12 -> 720720 | L11: =SUM(D11:K11) -> 720720 | M11: =22*26*12 -> 6864 | N11: =L11/M11 -> 105
A12: MAKINO 01 | B12: MAKINO | D12: =105*22*26*12 -> 720720 | L12: =SUM(D12:K12) -> 720720 | M12: =22*26*12 -> 6864 | N12: =L12/M12 -> 105
A13: MAKINO 02 | B13: MAKINO | D13: =105*22*26*12 -> 720720 | L13: =SUM(D13:K13) -> 720720 | M13: =22*26*12 -> 6864 | N13: =L13/M13 -> 105
A14: MAKINO 03 | B14: MAKINO | D14: =105*22*26*12 -> 720720 | L14: =SUM(D14:K14) -> 720720 | M14: =22*26*12 -> 6864 | N14: =L14/M14 -> 105
A15: LMW 01 | B15: LMW | D15: =105*22*26*12 -> 720720 | L15: =SUM(D15:K15) -> 720720 | M15: =22*26*12 -> 6864 | N15: =L15/M15 -> 105
... A23: VMC 400 - 1 | B23: AMS VMC | D23: =105*22*26*12 -> 720720 | L23: =SUM(D23:K23) -> 720720 | M23: =22*26*12 -> 6864 | N23: =L23/M23 -> 105

Sheet Sheet1
A1: Sr. No. | B1: Machine | C1: Type | D1: Make | E1: Qty | F1: Kw Each per Hour | G1: KW Total per Hour
A2: 1 | B2: EC- 400 /300 | C2: HMC | D2: HAAS | E2: 3 | F2: 19 | G2: 57
A3: 2 | B3: VF - 2 | C3: VMC | D3: HAAS | E3: 4 | F3: 19 | G3: 76
A4: 3 | B4: VF- 2 I & VF - 4 I | C4: VMC | D4: HAAS | E4: 1 | F4: 18 | G4: 18
A5: 4 | B5: Makino Slim -3 | C5: VMC | D5: Makino | E5: 3 | F5: 24 | G5: 72
A6: 5 | B6: LMW | C6: Turning Center | D6: LMW | E6: 2 | F6: 12 | G6: 24
A7: 6 | B7: MCV -350 | C7: VMC | D7: ACE | E7: 3 | F7: 18 | G7: 55
A8: 7 | B8: MCV -400 | C8: VMC | D8: ACE | E8: 1 | F8: 22 | G8: 22
A9: 8 | B9: Super Jobber | C9: Turning Center | D9: ACE | E9: 1 | F9: 17 | G9: 17
A10: 9 | B10: Junior Jobber | C10: Turning Center | D10: ACE | E10: 1 | F10: 13 | G10: 13
A11: 10 | B11: J300 LM | C11: Turning Center | D11: ACE | E11: 1 | F11: 11 | G11: 11
F12: Total KW | G12: 366
B14: Utility | C14: Type | D14: Make | E14: Qty | F14: Kw Each | G14: KW Total
A15: 1 | B15: Air Compressor | C15: Screw | D15: Atlas Copco | E15: 1 | F15: 12 | G15: 12
A16: 2 | B16: Illumination | C16: T/Lights | D16: Phillips | E16: 40 | F16: 0.8 | G16: 32
A17: 3 | B17: AC (5.5TR x 6Nos) | C17: Ductable split | D17: Voltas | E17: 6 | F17: 14 | G17: 86
F18: Total KW | G18: 130

Sheet Wax Shell Rate
A1: Shell Rate | B1: Nasik | C1: Nasik | D1: Mn | G1: 20300STR | M1: 20200STR
A2: Shell Rate | B2: MS | C2: SS | G2: Pattern Batch Regular KG | H2: Erp Code | I2: Qty | J2: Rate | K2: Value | M2: Pattern Batch Regular KG | N2: Erp Code | O2: Qty | P2: Rate | Q2: Value
A3: 20300STR | C3: =SUMIFS('Nasik Ledger'!N:N,'Nasik Ledger'!$A:$A,$A3,'Nasik Ledger'!$I:$I,"RMSL")+SUMIFS('Nasik Ledger'!P:P,'Nasik Ledger'!$A:$A,$A3,'Nasik Ledger'!$I:$I,"RMSL")+SUMIFS('Nasik Ledger'!N:N,'Nasik Ledger'!$A:$A,$A3,'Nasik Ledger'!$I:$I,"RMSI")+SUMIFS('Nasik Ledger'!P:P,'Nasik Ledger'!$A:$A,$A3,'Nasik Ledger'!$I:$I,"RMSI") -> -1894072.4 | D3: =SUMIFS('Nasik Ledger'!O:O,'Nasik Ledger'!$A:$A,$A3,'Nasik Ledger'!$I:$I,"RMSL")+SUMIFS('Nasik Ledger'!Q:Q,'Nasik Ledger'!$A:$A,$A3,'Nasik Ledger'!$I:$I,"RMSL")+SUMIFS('Nasik Ledger'!O:O,'Nasik Ledger'!$A:$A,$A3,'Nasik Ledger'!$I:$I,"RMSI")+SUMIFS('Nasik Ledger'!Q:Q,'Nasik Ledger'!$A:$A,$A3,'Nasik Ledger'!$I:$I,"RMSI") -> -59107117 | E3: 49 | G3: RD053 | H3: 0111014 | I3: 24 | J3: =VLOOKUP(CONCATENATE("'",$H3),'Nasik Ledger'!$F$3:$AB$957,21,0) -> 163.62033 | K3: =J3*I3 -> 3926.8879 | M3: RD053 | N3: 0111014 | O3: 24 | P3: =VLOOKUP(CONCATENATE("'",$N3),'Mn Ledger'!$F$3:$AB$957,21,0) -> 163.66812 | Q3: =P3*O3 -> 3928.0349
A4: 20200STR | C4: =SUMIFS('Mn Ledger'!N:N,'Mn Ledger'!$A:$A,$A4,'Mn Ledger'!$I:$I,"RMSL")+SUMIFS('Mn Ledger'!P:P,'Mn Ledger'!$A:$A,$A4,'Mn Ledger'!$I:$I,"RMSL")+SUMIFS('Mn Ledger'!N:N,'Mn Ledger'!$A:$A,$A4,'Mn Ledger'!$I:$I,"RMSI")+SUMIFS('Mn Ledger'!P:P,'Mn Ledger'!$A:$A,$A4,'Mn Ledger'!$I:$I,"RMSI") -> -1041637.5 | D4: =SUMIFS('Mn Ledger'!O:O,'Mn Ledger'!$A:$A,$A4,'Mn Ledger'!$I:$I,"RMSL")+SUMIFS('Mn Ledger'!Q:Q,'Mn Ledger'!$A:$A,$A4,'Mn Ledger'!$I:$I,"RMSL")+SUMIFS('Mn Ledger'!O:O,'Mn Ledger'!$A:$A,$A4,'Mn Ledger'!$I:$I,"RMSI")+SUMIFS('Mn Ledger'!Q:Q,'Mn Ledger'!$A:$A,$A4,'Mn Ledger'!$I:$I,"RMSI") -> -42056205 | E4: =D4/C4 -> 40.375087 | G4: RD001 | H4: 0111001 | I4: 3 | J4: =VLOOKUP(CONCATENATE("'",$H4),'Nasik Ledger'!$F$3:$AB$957,21,0) -> 129.21989 | K4: =J4*I4 -> 387.65966 | M4: RD001 | N4: 0111001 | O4: 3 | P4: =VLOOKUP(CONCATENATE("'",$N4),'Mn Ledger'!$F$3:$AB$957,21,0) -> 134.45535 | Q4: =P4*O4 -> 403.36605 | T4: To calculate Overhead for Wax
G5: RD020 | H5: 0111006 | I5: 2.5 | J5: =VLOOKUP(CONCATENATE("'",$H5),'Nasik Ledger'!$F$3:$AB$957,21,0) -> 420.34669 | K5: =J5*I5 -> 1050.8667 | M5: RD020 | N5: 0111006 | O5: 2.5 | P5: =VLOOKUP(CONCATENATE("'",$N5),'Mn Ledger'!$F$3:$AB$957,21,0) -> 420.64602 | Q5: =P5*O5 -> 1051.615 | T5: 1. Labour required
A6: Pattern Wax | B6: 81.79 | C6: 81.79 | D6: 81.81 | G6: RD105 | H6: 0111052 | I6: 2 | J6: =VLOOKUP(CONCATENATE("'",$H6),'Nasik Ledger'!$F$3:$AB$957,21,0) -> 497.22059 | K6: =J6*I6 -> 994.44117 | M6: RD105 | N6: 0111052 | O6: 2 | P6: =VLOOKUP(CONCATENATE("'",$N6),'Mn Ledger'!$F$3:$AB$957,21,0) -> 494.81074 | Q6: =P6*O6 -> 989.62149 | T6: 2. Power Required
A7: Riser Wax | B7: 13.88 | C7: 13.88 | D7: 13.82 | G7: RD011 | H7: 0111004 | I7: 1.5 | J7: =VLOOKUP(CONCATENATE("'",$H7),'Nasik Ledger'!$F$3:$AB$957,21,0) -> 126.95901 | K7: =J7*I7 -> 190.43851 | M7: RD011 | N7: 0111004 | O7: 1.5 | P7: =VLOOKUP(CONCATENATE("'",$N7),'Mn Ledger'!$F$3:$AB$957,21,0) -> 123.61997 | Q7: =P7*O7 -> 185.42996 | T7: 3. Depreciation
A8: Water Sol Wax | B8: 70 | C8: 70 | D8: 70 | G8: Reclaimed Wax | I8: 137 | J8: =J38 -> 7.3208557 | K8: =J8*I8 -> 1002.9572 | M8: Reclaimed Wax | O8: 137 | P8: =P38 -> 7.3215336 | Q8: =P8*O8 -> 1003.0501
A9: Ceramic Core | B9: 400 | C9: 400 | D9: 400 | G9: RD072/RD304 | H9: 0111022 | I9: 30 | J9: =VLOOKUP(CONCATENATE("'",$H9),'Nasik Ledger'!$F$3:$AB$957,21,0) -> 210 | K9: =J9*I9 -> 6300 | M9: RD072/RD304 | N9: 0111022 | O9: 30 | P9: =VLOOKUP(CONCATENATE("'",$N9),'Mn Ledger'!$F$3:$AB$957,21,0) -> 210 | Q9: =P9*O9 -> 6299.9999
A10: Shell Cost | B10: 42 | C10: 45 | D10: 39 | G10: Overhead | I10: 200 | J10: 10 | K10: =J10*I10 -> 2000 | M10: Overhead | O10: 200 | P10: 10 | Q10: =P10*O10 -> 2000
G11: Total | I11: 200 | J11: =K11/I11 -> 79.266256 | K11: =SUM(K3:K10) -> 15853.251 | M11: Total | O11: 200 | P11: =Q11/O11 -> 79.305587 | Q11: =SUM(Q3:Q10) -> 15861.117
A12: For 3M | B12: 120 | C12: Only for specific codes - Spinner, Impeller
G13: Pattern Batch 26E serries KG | M13: Pattern Batch 26E serries KG
G14: RD053 | H14: 0111014 | I14: 11.9 | J14: =VLOOKUP(CONCATENATE("'",$H14),'Nasik Ledger'!$F$3:$AB$957,21,0) -> 163.62033 | K14: =J14*I14 -> 1947.0819 | M14: RD053 | N14: 0111014 | O14: 11.9 | P14: =VLOOKUP(CONCATENATE("'",$N14),'Mn Ledger'!$F$3:$AB$957,21,0) -> 163.66812 | Q14: =P14*O14 -> 1947.6506
G15: RD001 | H15: 0111001 | I15: 2.45 | J15: =VLOOKUP(CONCATENATE("'",$H15),'Nasik Ledger'!$F$3:$AB$957,21,0) -> 129.21989 | K15: =J15*I15 -> 316.58873 | M15: RD001 | N15: 0111001 | O15: 2.45 | P15: =VLOOKUP(CONCATENATE("'",$N15),'Mn Ledger'!$F$3:$AB$957,21,0) -> 134.45535 | Q15: =P15*O15 -> 329.41561
G16: RD020 | H16: 0111006 | I16: 1.4 | J16: =VLOOKUP(CONCATENATE("'",$H16),'Nasik Ledger'!$F$3:$AB$957,21,0) -> 420.34669 | K16: =J16*I16 -> 588.48537 | M16: RD020 | N16: 0111006 | O16: 1.4 | P16: =VLOOKUP(CONCATENATE("'",$N16),'Mn Ledger'!$F$3:$AB$957,21,0) -> 420.64602 | Q16: =P16*O16 -> 588.90442
G17: RD105 | H17: 0111052 | I17: 1.05 | J17: =VLOOKUP(CONCATENATE("'",$H17),'Nasik Ledger'!$F$3:$AB$957,21,0) -> 497.22059 | K17: =J17*I17 -> 522.08161 | M17: RD105 | N17: 0111052 | O17: 1.05 | P17: =VLOOKUP(CONCATENATE("'",$N17),'Mn Ledger'!$F$3:$AB$957,21,0) -> 494.81074 | Q17: =P17*O17 -> 519.55128
G18: RD011 | H18: 0111004 | I18: 0.7 | J18: =VLOOKUP(CONCATENATE("'",$H18),'Nasik Ledger'!$F$3:$AB$957,21,0) -> 126.95901 | K18: =J18*I18 -> 88.871306 | M18: RD011 | N18: 0111004 | O18: 0.7 | P18: =VLOOKUP(CONCATENATE("'",$N18),'Mn Ledger'!$F$3:$AB$957,21,0) -> 123.61997 | Q18: =P18*O18 -> 86.533982
G19: Reclaimed Wax | I19: 57.5 | J19: =J38 -> 7.3208557 | K19: =J19*I19 -> 420.9492 | M19: Reclaimed Wax | O19: 57.5 | P19: =P38 -> 7.3215336 | Q19: =P19*O19 -> 420.98818
G20: RD072 | H20: 0111022 | I20: 15 | J20: =VLOOKUP(CONCATENATE("'",$H20),'Nasik Ledger'!$F$3:$AB$957,21,0) -> 210 | K20: =J20*I20 -> 3150 | M20: RD072 | N20: 0111022 | O20: 15 | P20: =VLOOKUP(CONCATENATE("'",$N20),'Mn Ledger'!$F$3:$AB$957,21,0) -> 210 | Q20: =P20*O20 -> 3149.9999
G21: RD 304 | H21: 0111073 | I21: 10 | J21: 210 | K21: =J21*I21 -> 2100 | M21: RD 304 | N21: 0111073 | O21: 10 | P21: 210 | Q21: =P21*O21 -> 2100
G22: Overhead | I22: 100 | J22: 10 | K22: =J22*I22 -> 1000 | M22: Overhead | O22: 100 | P22: 10 | Q22: =P22*O22 -> 1000
G23: TOTAL | I23: 100 | J23: =K23/I23 -> 101.34058 | K23: =SUM(K14:K22) -> 10134.058 | M23: TOTAL | O23: 100 | P23: =Q23/O23 -> 101.43044 | Q23: =SUM(Q14:Q22) -> 10143.044
G25: Riser Batch KG | M25: Riser Batch KG
G26: RECLAIM WAX | I26: 80 | J26: =J38 -> 7.3208557 | K26: =J26*I26 -> 585.66846 | M26: RECLAIM WAX | O26: 80 | P26: =P38 -> 7.3215336 | Q26: =P26*O26 -> 585.72269
G27: FILTER WAX | I27: 60 | J27: 0 | K27: 0 | M27: FILTER WAX | O27: 60 | P27: 0 | Q27: =P27*O27 -> 0
G28: RD 001 | H28: 0111001 | I28: 3 | J28: =VLOOKUP(CONCATENATE("'",$H28),'Nasik Ledger'!$F$3:$AB$957,21,0) -> 129.21989 | K28: =J28*I28 -> 387.65966 | M28: RD 001 | N28: 0111001 | O28: 3 | P28: =VLOOKUP(CONCATENATE("'",$N28),'Mn Ledger'!$F$3:$AB$957,21,0) -> 134.45535 | Q28: =P28*O28 -> 403.36605
G29: RD 011 | H29: 0111004 | I29: 2 | J29: =VLOOKUP(CONCATENATE("'",$H29),'Nasik Ledger'!$F$3:$AB$957,21,0) -> 126.95901 | K29: =J29*I29 -> 253.91802 | M29: RD 011 | N29: 0111004 | O29: 2 | P29: =VLOOKUP(CONCATENATE("'",$N29),'Mn Ledger'!$F$3:$AB$957,21,0) -> 123.61997 | Q29: =P29*O29 -> 247.23995
G30: Overhead | I30: 145 | J30: 5 | K30: =J30*I30 -> 725 | M30: Overhead | O30: 145 | P30: 5 | Q30: =P30*O30 -> 725
G31: TOTAL | I31: 145 | J31: =K31/I31 -> 13.463766 | K31: =SUM(K26:K30) -> 1952.2461 | M31: TOTAL | O31: 145 | P31: =Q31/O31 -> 13.526405 | Q31: =SUM(Q26:Q30) -> 1961.3287
G34: Reclaim Batch Kg | M34: Reclaim Batch Kg
G35: SETTELED WAX/FILTERED WAX | I35: 139 | J35: 0 | K35: 0 | M35: SETTELED WAX/FILTERED WAX | O35: 139 | P35: 0 | Q35: 0
G36: RD053 | H36: 0111014 | I36: 2 | J36: =VLOOKUP(CONCATENATE("'",$H36),'Nasik Ledger'!$F$3:$AB$957,21,0) -> 163.62033 | K36: =J36*I36 -> 327.24066 | M36: RD053 | N36: 0111014 | O36: 2 | P36: =VLOOKUP(CONCATENATE("'",$N36),'Mn Ledger'!$F$3:$AB$957,21,0) -> 163.66812 | Q36: =P36*O36 -> 327.33624
G37: Overhead | I37: 141 | J37: 5 | K37: =J37*I37 -> 705 | M37: Overhead | O37: 141 | P37: 5 | Q37: =P37*O37 -> 705
G38: TOTAL | I38: 141 | J38: =K38/I38 -> 7.3208557 | K38: =SUM(K35:K37) -> 1032.2407 | M38: TOTAL | O38: 141 | P38: =Q38/O38 -> 7.3215336 | Q38: =SUM(Q35:Q37) -> 1032.3362

Sheet Testing Charges Calculations
A1: Chemical Analysis | C1: Labour
A2: Tensile Test | C2: Power
A3: Impact Test | C3: Depreciation
A4: Bend Test | C4: Consumables
A5: Metallography | C5: Maintenance
A6: IGCT | C6: Maintenance Spares
A7: LP/DP | C7: Overhead
A8: Magnetic Particle
A9: Radiography
A10: Any Other

Sheet Exchange Rate
A1: Curr | B1: Rate
A2: USD | B2: 82.46
A3: GBP | B3: 91
A4: EUR | B4: 81.22
A5: INR | B5: 1

Sheet Master
B1: Mn | C1: Nasik | D1: Nasik | E1: UOM | I1: Avg Std Mld Wt
C2: MS | D2: SS
A3: Overhead | B3: 389 | C3: 1621.88 | D3: 1696.12 | E3: Per Mould | H3: Nasik | I3: 27 | J3: Mould Wt in Kg
A4: Labour | B4: 537 | C4: 488 | D4: 488 | E4: Per Mould | H4: Mn | I4: 23 | J4: Mould Wt in Kg
A5: Heat Treatment | B5: 0 | C5: 0 | D5: 0 | E5: Actual
A6: Consumables | B6: 319 | C6: 645.02 | D6: 706.98 | E6: Per Mould
A7: Power | B7: 24 | C7: 26 | D7: 26 | E7: Per Kg
A8: Fuel | E8: Per Mould
A9: Meting Loss | B9: 0.03 | C9: 0.03 | D9: 0.03 | E9: Percentage
A10: Margin % | B10: 0 | C10: =B10 -> 0 | D10: =B10 -> 0 | E10: Enter in % e.g. for 13 % enter "13%"
A11: Metal Rate Fluctuation | B11: 0 | C11: 0 | D11: 0 | E11: Percentage
A28: Machine Shop | B28: Total Amount | C28: Per Hr Rate
A29: Labour | B29: =9956434+6500000 -> 16456434 | C29: =B29/$B$35 -> 123.5635
A30: Power | B30: 3539178 | C30: =B30/$B$35 -> 26.573996
A31: Consumables | B31: 6075345 | C31: =B31/$B$35 -> 45.616863
A35: Time Available | B35: =21*302*21 -> 133182
A37: Machine Type | B37: Rate / Hr
A38: HMC | B38: 1000
A39: VMC | B39: 650
A40: MAKINO | B40: 600
A41: LMW | B41: 180
A42: ACE | B42: 180
A43: AMS VMC | B43: 480

Sheet Nasik Ledger
I1: B/p GL | J1: Opening Stock | K1: Opening Stock | L1: RECEIPT | M1: RECEIPT | N1: SIR | O1: SIR | P1: IGR | Q1: IGR | R1: SALES | S1: SALES | T1: TRASNFER | U1: TRASNFER | V1: Other Tran | W1: Other Tran | X1: Closing Stock | Y1: Closing Stock
A2: Branch Plant | B2: From Date | C2: To Date | D2: From Date | E2: To Date | F2: Item Code | G2: Description | H2: UOM | I2: Code | J2: Qty | K2: Amount | L2: Qty | M2: Amount | N2: Qty | O2: Amount | P2: Qty | Q2: Amount | R2: Qty | S2: Amount | T2: Qty | U2: Amount | V2: Qty | W2: Amount | X2: Qty | Y2: Amount | Z2: Rate
A3: 20300STR | B3: 44287 | C3: 44651 | D3: 20210401 | E3: 20220331 | F3: '001T0128D | G3: 1T128 FOUR CAVITY WAX INJ. | H3: NO | I3: TLL | P3: 1 | R3: -1 | Z3: =IFERROR((O3+Q3)/(N3+P3),Y3/X3) -> 0
A4: 20300STR | B4: 44287 | C4: 44651 | D4: 20210401 | E4: 20220331 | F4: '001T0155D | G4: 1T155 FOUR CAVITY WAX INJE. | H4: NO | I4: TLL | P4: 1 | Q4: 111000 | R4: -1 | S4: -111000 | Z4: =IFERROR((O4+Q4)/(N4+P4),Y4/X4) -> 111000
A5: 20300STR | B5: 44287 | C5: 44651 | D5: 20210401 | E5: 20220331 | F5: '001T0156D | G5: 1T156 FOUR CAVITY WAX MOULD | H5: NO | I5: TLL | P5: 1 | R5: -1 | Z5: =IFERROR((O5+Q5)/(N5+P5),Y5/X5) -> 0
A6: 20300STR | B6: 44287 | C6: 44651 | D6: 20210401 | E6: 20220331 | F6: '001T0162D | G6: 1T162 FOUR CAVITY WAX INJE. | H6: NO | I6: TLL | L6: 1 | M6: 110000 | N6: -1 | O6: -110000 | P6: 1 | Q6: 110000 | R6: -1 | S6: -110000 | Z6: =IFERROR((O6+Q6)/(N6+P6),Y6/X6) -> #DIV/0!
A7: 20300STR | B7: 44287 | C7: 44651 | D7: 20210401 | E7: 20220331 | F7: '001T0165D | G7: 1T165/138 TWO CAVITY WAX INJ. | H7: NO | I7: TLL | P7: 1 | R7: -1 | Z7: =IFERROR((O7+Q7)/(N7+P7),Y7/X7) -> 0
A8: 20300STR | B8: 44287 | C8: 44651 | D8: 20210401 | E8: 20220331 | F8: '001T0196D | G8: 1T196 TWO CAVITY WAX INJ.MOULD | H8: NO | I8: TLL | L8: 1 | M8: 220000 | N8: -1 | O8: -220000 | Z8: =IFERROR((O8+Q8)/(N8+P8),Y8/X8) -> 220000
A9: 20300STR | B9: 44287 | C9: 44651 | D9: 20210401 | E9: 20220331 | F9: '001T0199D | G9: 1T199 TWO CAVITY WAX INJECTION | H9: NO | I9: TLL | P9: 1 | R9: -1 | Z9: =IFERROR((O9+Q9)/(N9+P9),Y9/X9) -> 0
A10: 20300STR | B10: 44287 | C10: 44651 | D10: 20210401 | E10: 20220331 | F10: '001T0200D | G10: 1T200 TWO CAVITY WAX INJ. DIE | H10: NO | I10: TLL | P10: 1 | Q10: 95450 | R10: -1 | S10: -95450 | Z10: =IFERROR((O10+Q10)/(N10+P10),Y10/X10) -> 95450
A11: 20300STR | B11: 44287 | C11: 44651 | D11: 20210401 | E11: 20220331 | F11: '001T0203D | G11: 1T203 TWO CAVITY WAX INJECTION | H11: NO | I11: TLL | P11: 1 | Q11: 100729 | R11: -1 | S11: -100729 | Z11: =IFERROR((O11+Q11)/(N11+P11),Y11/X11) -> 100729
A12: 20300STR | B12: 44287 | C12: 44651 | D12: 20210401 | E12: 20220331 | F12: '001T0204D | G12: 1T204 TWO CAVITY WAX INJECTION | H12: NO | I12: TLL | P12: 1 | Q12: 101971 | R12: -1 | S12: -101971 | Z12: =IFERROR((O12+Q12)/(N12+P12),Y12/X12) -> 101971
A13: 20300STR | B13: 44287 | C13: 44651 | D13: 20210401 | E13: 20220331 | F13: '001T0205D | G13: 1T205 TWO CAVITY WAX INJECTION | H13: NO | I13: TLL | P13: 1 | Q13: 92541 | R13: -1 | S13: -92541 | Z13: =IFERROR((O13+Q13)/(N13+P13),Y13/X13) -> 92541
A14: 20300STR | B14: 44287 | C14: 44651 | D14: 20210401 | E14: 20220331 | F14: '001T0210D | G14: 1T210 SINGLE CAVITY WAX INJ. | H14: NO | I14: TLL | P14: 1 | Q14: 110000 | R14: -1 | S14: -110000 | Z14: =IFERROR((O14+Q14)/(N14+P14),Y14/X14) -> 110000
A15: 20300STR | B15: 44287 | C15: 44651 | D15: 20210401 | E15: 20220331 | F15: '001T0210RD | G15: 1T210 RISER MOULD WITH | H15: NO | I15: TLL | P15: 1 | Q15: 42000 | R15: -1 | S15: -42000 | Z15: =IFERROR((O15+Q15)/(N15+P15),Y15/X15) -> 42000
A16: 20300STR | B16: 44287 | C16: 44651 | D16: 20210401 | E16: 20220331 | F16: '001T0213D | G16: 1T213 TWO CAVITY WAX INJECTION | H16: NO | I16: TLL | P16: 1 | Q16: 65000 | R16: -1 | S16: -65000 | Z16: =IFERROR((O16+Q16)/(N16+P16),Y16/X16) -> 65000
A17: 20300STR | B17: 44287 | C17: 44651 | D17: 20210401 | E17: 20220331 | F17: '001T0214D | G17: 1T214 TWO CAVITY WAX INJECTION | H17: NO | I17: TLL | P17: 1 | Q17: 78000 | R17: -1 | S17: -78000 | Z17: =IFERROR((O17+Q17)/(N17+P17),Y17/X17) -> 78000
A18: 20300STR | B18: 44287 | C18: 44651 | D18: 20210401 | E18: 20220331 | F18: '001TC207 | G18: CERAMIC CORE 2T207 | H18: NO | I18: CONS | K18: 0.01 | L18: 41139 | M18: 1439865 | N18: -41139 | O18: -1439865 | Y18: 0.01 | Z18: =IFERROR((O18+Q18)/(N18+P18),Y18/X18) -> 35
A19: 20300STR | B19: 44287 | C19: 44651 | D19: 20210401 | E19: 20220331 | F19: '002T0040D | G19: 2T40 MAIN DIE | H19: NO | I19: TLL | P19: 1 | Q19: 77000 | R19: -1 | S19: -77000 | Z19: =IFERROR((O19+Q19)/(N19+P19),Y19/X19) -> 77000
A20: 20300STR | B20: 44287 | C20: 44651 | D20: 20210401 | E20: 20220331 | F20: '002T0052D | G20: 2T52 TWO CAVITY WAX MOULD | H20: NO | I20: TLL | P20: 1 | R20: -1 | Z20: =IFERROR((O20+Q20)/(N20+P20),Y20/X20) -> 0
A21: 20300STR | B21: 44287 | C21: 44651 | D21: 20210401 | E21: 20220331 | F21: '002T0053D | G21: 2T53 TWO CAVITY WAX MOULD | H21: NO | I21: TLL | P21: 1 | R21: -1 | Z21: =IFERROR((O21+Q21)/(N21+P21),Y21/X21) -> 0
A22: 20300STR | B22: 44287 | C22: 44651 | D22: 20210401 | E22: 20220331 | F22: '002T0054D | G22: 2T54 TWO CAVITY WAX MOULD | H22: NO | I22: TLL | P22: 1 | R22: -1 | Z22: =IFERROR((O22+Q22)/(N22+P22),Y22/X22) -> 0
A23: 20300STR | B23: 44287 | C23: 44651 | D23: 20210401 | E23: 20220331 | F23: '002T0055D | G23: 2T55 TWO CAVITY WAX MOULD | H23: NO | I23: TLL | P23: 1 | R23: -1 | Z23: =IFERROR((O23+Q23)/(N23+P23),Y23/X23) -> 0
A24: 20300STR | B24: 44287 | C24: 44651 | D24: 20210401 | E24: 20220331 | F24: '002T0056D | G24: 2T56 TWO CAVITY WAX MOULD | H24: NO | I24: TLL | P24: 1 | R24: -1 | Z24: =IFERROR((O24+Q24)/(N24+P24),Y24/X24) -> 0
A25: 20300STR | B25: 44287 | C25: 44651 | D25: 20210401 | E25: 20220331 | F25: '002T0057CD | G25: 2T57 TWO CAVITY WAX CHILL | H25: NO | I25: TLL | P25: 1 | R25: -1 | Z25: =IFERROR((O25+Q25)/(N25+P25),Y25/X25) -> 0
A26: 20300STR | B26: 44287 | C26: 44651 | D26: 20210401 | E26: 20220331 | F26: '002T0057D | G26: 2T57 TWO CAVITY WAX MAIN | H26: NO | I26: TLL | P26: 1 | R26: -1 | Z26: =IFERROR((O26+Q26)/(N26+P26),Y26/X26) -> 0
A27: 20300STR | B27: 44287 | C27: 44651 | D27: 20210401 | E27: 20220331 | F27: '002T0058D | G27: 2T58 TWO CAVITY WAX MOULD | H27: NO | I27: TLL | P27: 1 | R27: -1 | Z27: =IFERROR((O27+Q27)/(N27+P27),Y27/X27) -> 0
A28: 20300STR | B28: 44287 | C28: 44651 | D28: 20210401 | E28: 20220331 | F28: '003Y0026D | G28: 3Y26 SINGLE CAVITY WAX | H28: NO | I28: TLL | L28: 1 | M28: 115000 | N28: -1 | O28: -115000 | Z28: =IFERROR((O28+Q28)/(N28+P28),Y28/X28) -> 115000
A29: 20300STR | B29: 44287 | C29: 44651 | D29: 20210401 | E29: 20220331 | F29: '003Y0032 | G29: DISCONNECTOR CAM | H29: NO | I29: TRAD | L29: 158 | M29: 17854 | N29: -158 | O29: -17854 | Z29: =IFERROR((O29+Q29)/(N29+P29),Y29/X29) -> 113
A30: 20300STR | B30: 44287 | C30: 44651 | D30: 20210401 | E30: 20220331 | F30: '003Y0035 | G30: ISOLATER EYE BOLT | H30: NO | I30: TRAD | L30: 29 | M30: 5046 | N30: -29 | O30: -5046 | Z30: =IFERROR((O30+Q30)/(N30+P30),Y30/X30) -> 174
A31: 20300STR | B31: 44287 | C31: 44651 | D31: 20210401 | E31: 20220331 | F31: '003Y0042D | G31: 3Y42 FOUR CAVITY WAX INJECTION | H31: NO | I31: TLL | P31: 1 | Q31: 28000 | R31: -1 | S31: -28000 | Z31: =IFERROR((O31+Q31)/(N31+P31),Y31/X31) -> 28000
A32: 20300STR | B32: 44287 | C32: 44651 | D32: 20210401 | E32: 20220331 | F32: '007U0599D | G32: 7U599 TWO CAVITY WAX INJECTION | H32: NO | I32: TLL | L32: 1 | M32: 158000 | N32: -1 | O32: -158000 | P32: 1 | Q32: 158000 | R32: -1 | S32: -158000 | Z32: =IFERROR((O32+Q32)/(N32+P32),Y32/X32) -> #DIV/0!
A33: 20300STR | B33: 44287 | C33: 44651 | D33: 20210401 | E33: 20220331 | F33: '0101002 | G33: ALUMINIUM SCRAP | H33: KG | I33: RMFL | J33: 219.8 | K33: 25253.32 | L33: 1437.1 | M33: 312009.08 | N33: -1596.17 | O33: -322769.96 | P33: 2.38 | Q33: 582.5 | R33: -60 | S33: -14244.04 | X33: 3.11 | Y33: 830.9 | Z33: =IFERROR((O33+Q33)/(N33+P33),Y33/X33) -> 202.15176
A34: 20300STR | B34: 44287 | C34: 44651 | D34: 20210401 | E34: 20220331 | F34: '0101007 | G34: BISMUTH ( LOCAL ] | H34: KG | I34: RMFL | J34: 1.09 | K34: 1692.23 | X34: 1.09 | Y34: 1692.23 | Z34: =IFERROR((O34+Q34)/(N34+P34),Y34/X34) -> 1552.5046
A35: 20300STR | B35: 44287 | C35: 44651 | D35: 20210401 | E35: 20220331 | F35: '0101013 | G35: CHROMIUM ( INDIGENOUS ) | H35: KG | I35: RMFL | L35: 3700 | M35: 2681150 | N35: -3666.2 | O35: -2635669.9 | P35: 49.42 | Q35: 28891.55 | X35: 83.22 | Y35: 74371.64 | Z35: =IFERROR((O35+Q35)/(N35+P35),Y35/X35) -> 720.74562
A36: 20300STR | B36: 44287 | C36: 44651 | D36: 20210401 | E36: 20220331 | F36: '0101015 | G36: COBALT CATHODE- INDO NATIONAL | H36: KG | I36: RMFL | J36: 6.6 | K36: 18857.01 | L36: 80 | M36: 382200 | N36: -36.85 | O36: -146031.07 | P36: 3.2 | Q36: 11242.91 | X36: 52.95 | Y36: 266268.85 | Z36: =IFERROR((O36+Q36)/(N36+P36),Y36/X36) -> 4005.5917
A37: 20300STR | B37: 44287 | C37: 44651 | D37: 20210401 | E37: 20220331 | F37: '0101017 | G37: COPPER SCRAP ( RETURNS ) | H37: KG | I37: RMFR | J37: 220 | K37: 66213.4 | X37: 220 | Y37: 66213.4 | Z37: =IFERROR((O37+Q37)/(N37+P37),Y37/X37) -> 300.97
A38: 20300STR | B38: 44287 | C38: 44651 | D38: 20210401 | E38: 20220331 | F38: '0101019 | G38: COPPER SCRAP (PURCHASES) | H38: KG | I38: RMFL | J38: 139.88 | K38: 88124.77 | L38: 1145.6 | M38: 830917.16 | N38: -1272.25 | O38: -907571.67 | P38: 26.5 | Q38: 19118.58 | X38: 39.73 | Y38: 30588.84 | Z38: =IFERROR((O38+Q38)/(N38+P38),Y38/X38) -> 713.18731
A39: 20300STR | B39: 44287 | C39: 44651 | D39: 20210401 | E39: 20220331 | F39: '0101021 | G39: FERRO SILICO CALCIUM | H39: KG | I39: RMFL | J39: 65.48 | K39: 8376.49 | L39: 7920 | M39: 2137751 | N39: -6976.606 | O39: -1830116 | P39: 10.026 | Q39: 3325.95 | R39: -201 | S39: -46597.64 | X39: 817.9 | Y39: 272739.76 | Z39: =IFERROR((O39+Q39)/(N39+P39),Y39/X39) -> 262.22194
A40: 20300STR | B40: 44287 | C40: 44651 | D40: 20210401 | E40: 20220331 | F40: '0101059 | G40: MANGANESE METAL | H40: KG | I40: RMFL | J40: 793.92 | K40: 165873.47 | L40: 5578.608 | M40: 2328028.6 | N40: -5724.139 | O40: -2189016.7 | P40: 42.944 | Q40: 18349.55 | V40: -300 | W40: -110668.73 | X40: 391.333 | Y40: 212566.19 | Z40: =IFERROR((O40+Q40)/(N40+P40),Y40/X40) -> 382.07932
A41: 20300STR | B41: 44287 | C41: 44651 | D41: 20210401 | E41: 20220331 | F41: '0101061 | G41: MOLYBDENUM | H41: KG | I41: RMFL | J41: 11.74 | K41: 27002 | L41: 150 | M41: 513750 | N41: -16.67 | O41: -43985.11 | X41: 145.07 | Y41: 496766.89 | Z41: =IFERROR((O41+Q41)/(N41+P41),Y41/X41) -> 2638.5789
A42: 20300STR | B42: 44287 | C42: 44651 | D42: 20210401 | E42: 20220331 | F42: '0101066 | G42: NICKEL BRIQUTTIES LOCAL | H42: KG | I42: RMFL | J42: 986.435 | K42: 1304406.5 | L42: 4761.6 | M42: 7422886.5 | N42: -4384.42 | O42: -6391705.2 | P42: 73.615 | Q42: 123680.38 | R42: -130 | S42: -169164.65 | V42: -990 | W42: -1431050.7 | X42: 317.23 | Y42: 859052.87 | Z42: =IFERROR((O42+Q42)/(N42+P42),Y42/X42) -> 1454.0265
A43: 20300STR | B43: 44287 | C43: 44651 | D43: 20210401 | E43: 20220331 | F43: '0101068 | G43: NICKEL 4"X4" | H43: KG | I43: RMFL | L43: 2850 | M43: 4601874.7 | N43: -2580.967 | O43: -4164262.2 | P43: 6.2 | Q43: 9889.91 | V43: -160 | W43: -259557.9 | X43: 115.233 | Y43: 187944.54 | Z43: =IFERROR((O43+Q43)/(N43+P43),Y43/X43) -> 1613.4945
A44: 20300STR | B44: 44287 | C44: 44651 | D44: 20210401 | E44: 20220331 | F44: '0101071 | G44: NICKEL CATHODE 1"X1" SQUARE | H44: KG | I44: RMFL | L44: 900 | M44: 1472000 | N44: -811.45 | O44: -1323769.8 | P44: 1.45 | Q44: 2414.34 | R44: -90 | S44: -146053.38 | W44: -4591.28 | Y44: -0.07 | Z44: =IFERROR((O44+Q44)/(N44+P44),Y44/X44) -> 1631.303
A45: 20300STR | B45: 44287 | C45: 44651 | D45: 20210401 | E45: 20220331 | F45: '0101085 | G45: SELLINIUM (PURCHASE &RETURNS) | H45: KG | I45: RMFL | J45: 1.56 | K45: 1002.56 | X45: 1.56 | Y45: 1002.56 | Z45: =IFERROR((O45+Q45)/(N45+P45),Y45/X45) -> 642.66667
A46: 20300STR | B46: 44287 | C46: 44651 | D46: 20210401 | E46: 20220331 | F46: '0101090 | G46: TIN [ LOCAL ] | H46: KG | I46: RMFL | J46: 1.37 | K46: 1851.02 | X46: 1.37 | Y46: 1851.02 | Z46: =IFERROR((O46+Q46)/(N46+P46),Y46/X46) -> 1351.1095
A47: 20300STR | B47: 44287 | C47: 44651 | D47: 20210401 | E47: 20220331 | F47: '0101093 | G47: PURE TUNGSTON | H47: KG | I47: RMFL | J47: 8.72 | K47: 19036.08 | L47: 49 | M47: 129600 | N47: -12.4 | O47: -27867.34 | P47: 0.99 | Q47: 2537.88 | X47: 46.31 | Y47: 123306.62 | Z47: =IFERROR((O47+Q47)/(N47+P47),Y47/X47) -> 2219.9351
A48: 20300STR | B48: 44287 | C48: 44651 | D48: 20210401 | E48: 20220331 | F48: '0101105 | G48: AL.STRONSIUM | H48: KG | I48: RMFL | J48: 10.8 | K48: 2618.78 | X48: 10.8 | Y48: 2618.78 | Z48: =IFERROR((O48+Q48)/(N48+P48),Y48/X48) -> 242.47963
A49: 20300STR | B49: 44287 | C49: 44651 | D49: 20210401 | E49: 20220331 | F49: '0101142 | G49: EXTRA LOW CARBON M.S.SCRAP | H49: KG | I49: RMFL | J49: 6149.2 | K49: 350504.4 | L49: 29700 | M49: 2011000 | N49: -36077.31 | O49: -2376523.7 | P49: 329.4 | Q49: 22108.56 | X49: 101.29 | Y49: 7089.23 | Z49: =IFERROR((O49+Q49)/(N49+P49),Y49/X49) -> 65.861617
A50: 20300STR | B50: 44287 | C50: 44651 | D50: 20210401 | E50: 20220331 | F50: '0101158 | G50: PURE IRON FLAKES C-0.01% | H50: KG | I50: RMFL | L50: 668.8 | M50: 48822.4 | N50: -672.08 | O50: -49061.84 | P50: 3.28 | Q50: 239.44 | Z50: =IFERROR((O50+Q50)/(N50+P50),Y50/X50) -> 73
A51: 20300STR | B51: 44287 | C51: 44651 | D51: 20210401 | E51: 20220331 | F51: '0101179 | G51: ALLUMINIUM PLATE 6082T6 | H51: KG | I51: RMTL | J51: 58 | K51: 18883.54 | N51: -58 | O51: -18883.54 | Z51: =IFERROR((O51+Q51)/(N51+P51),Y51/X51) -> 325.57828
A52: 20300STR | B52: 44287 | C52: 44651 | D52: 20210401 | E52: 20220331 | F52: '0101184 | G52: RM4 INGOT | H52: KG | I52: RMFI | K52: 0.26 | L52: 105635.75 | M52: 95.95 | N52: -93610.726 | O52: -127.62 | P52: 215.219 | Q52: -0.28 | X52: 12240.243 | Y52: -31.69 | Z52: =IFERROR((O52+Q52)/(N52+P52),Y52/X52) -> 0.0013694449
A53: 20300STR | B53: 44287 | C53: 44651 | D53: 20210401 | E53: 20220331 | F53: '0101185 | G53: RM4 REVERT | H53: KG | I53: RMFI | J53: 414.71 | K53: 463967.3 | X53: 414.71 | Y53: 463967.3 | Z53: =IFERROR((O53+Q53)/(N53+P53),Y53/X53) -> 1118.7753
A54: 20300STR | B54: 44287 | C54: 44651 | D54: 20210401 | E54: 20220331 | F54: '0101188 | G54: PURE IRON BRIQUETS | H54: KG | I54: RMFL | J54: 250.88 | K54: 15052.8 | L54: 3610 | M54: 268480 | N54: -4163.754 | O54: -306070.36 | P54: 341.506 | Q54: 26109.59 | X54: 38.632 | Y54: 3572.03 | Z54: =IFERROR((O54+Q54)/(N54+P54),Y54/X54) -> 73.245056
A55: 20300STR | B55: 44287 | C55: 44651 | D55: 20210401 | E55: 20220331 | F55: '0101190 | G55: FERRO SILICO CALCIUM | H55: KG | I55: RMFL | L55: 500 | M55: 155500 | X55: 500 | Y55: 155500 | Z55: =IFERROR((O55+Q55)/(N55+P55),Y55/X55) -> 311
A56: 20300STR | B56: 44287 | C56: 44651 | D56: 20210401 | E56: 20220331 | F56: '0102002 | G56: FERRO BORON | H56: KG | I56: RMFL | J56: 39 | K56: 7799.61 | X56: 39 | Y56: 7799.61 | Z56: =IFERROR((O56+Q56)/(N56+P56),Y56/X56) -> 199.99
A57: 20300STR | B57: 44287 | C57: 44651 | D57: 20210401 | E57: 20220331 | F57: '0102012 | G57: FERRO CHROME L. C. .03C | H57: KG | I57: RMFL | J57: 1692.26 | K57: 360899.42 | L57: 11859.2 | M57: 3874565 | N57: -12733.31 | O57: -3930264.4 | P57: 113.65 | Q57: 37929.32 | X57: 931.8 | Y57: 343129.33 | Z57: =IFERROR((O57+Q57)/(N57+P57),Y57/X57) -> 308.43423
A58: 20300STR | B58: 44287 | C58: 44651 | D58: 20210401 | E58: 20220331 | F58: '0102017 | G58: FERRO CHROME L.C. 0.1C | H58: KG | I58: RMFL | J58: 915.6 | K58: 160200.75 | L58: 37697.4 | M58: 10309942 | N58: -34416.73 | O58: -9294464.9 | P58: 276.977 | Q58: 78139.08 | R58: -3422 | S58: -894138.57 | X58: 1051.247 | Y58: 359678.35 | Z58: =IFERROR((O58+Q58)/(N58+P58),Y58/X58) -> 269.95877
A59: 20300STR | B59: 44287 | C59: 44651 | D59: 20210401 | E59: 20220331 | F59: '0102034 | G59: IRON SULPHIDE | H59: KG | I59: RMFL | J59: 3.72 | K59: 120.97 | L59: 160 | M59: 4600 | N59: -121.123 | O59: -3517.35 | P59: 0.48 | Q59: 14.66 | R59: -6 | S59: -180.08 | X59: 37.077 | Y59: 1038.2 | Z59: =IFERROR((O59+Q59)/(N59+P59),Y59/X59) -> 29.033512
A60: 20300STR | B60: 44287 | C60: 44651 | D60: 20210401 | E60: 20220331 | F60: '0102047 | G60: FERRO MANGANES M.C | H60: KG | I60: RMFL | L60: 19.5 | M60: 1888.77 | X60: 19.5 | Y60: 1888.77 | Z60: =IFERROR((O60+Q60)/(N60+P60),Y60/X60) -> 96.86
A61: 20300STR | B61: 44287 | C61: 44651 | D61: 20210401 | E61: 20220331 | F61: '0102048 | G61: FERRO MOLYBDENUM | H61: KG | I61: RMFL | J61: 252 | K61: 320335.98 | L61: 2916 | M61: 6008082.5 | N61: -3007.903 | O61: -5962724.1 | P61: 50.605 | Q61: 103388.52 | R61: -64 | S61: -133768.53 | X61: 146.702 | Y61: 335314.34 | Z61: =IFERROR((O61+Q61)/(N61+P61),Y61/X61) -> 1981.3139
A62: 20300STR | B62: 44287 | C62: 44651 | D62: 20210401 | E62: 20220331 | F62: '0102049 | G62: HIGH CARBON FERRO MANGANES | H62: KG | I62: RMFL | L62: 150 | M62: 15700 | N62: -100.245 | O62: -10476.65 | P62: 5.445 | Q62: 572.67 | X62: 55.2 | Y62: 5796.02 | Z62: =IFERROR((O62+Q62)/(N62+P62),Y62/X62) -> 104.47236
A63: 20300STR | B63: 44287 | C63: 44651 | D63: 20210401 | E63: 20220331 | F63: '0102056 | G63: FERRO NOIBIUM | H63: KG | I63: RMFL | J63: 60.48 | K63: 128528.98 | L63: 204 | M63: 528398.48 | N63: -250.485 | O63: -620093.16 | P63: 1.455 | Q63: 3317.87 | X63: 15.45 | Y63: 40152.17 | Z63: =IFERROR((O63+Q63)/(N63+P63),Y63/X63) -> 2476.7108
A64: 20300STR | B64: 44287 | C64: 44651 | D64: 20210401 | E64: 20220331 | F64: '0102061 | G64: SILICON METAL | H64: KG | I64: RMFL | J64: 439.9 | K64: 58803.6 | L64: 667 | M64: 225110 | N64: -864.475 | O64: -197386.42 | P64: 23.93 | Q64: 4715.05 | X64: 266.355 | Y64: 91242.23 | Z64: =IFERROR((O64+Q64)/(N64+P64),Y64/X64) -> 229.22196
A65: 20300STR | B65: 44287 | C65: 44651 | D65: 20210401 | E65: 20220331 | F65: '0102074 | G65: FERRO SILICON | H65: KG | I65: RMFL | J65: 647.16 | K65: 70253.82 | L65: 9028.5 | M65: 1568969.2 | N65: -8448.72 | O65: -1408335.1 | P65: 75.963 | Q65: 11829.92 | R65: -550 | S65: -85809.17 | X65: 752.903 | Y65: 156908.65 | Z65: =IFERROR((O65+Q65)/(N65+P65),Y65/X65) -> 166.79156
A66: 20300STR | B66: 44287 | C66: 44651 | D66: 20210401 | E66: 20220331 | F66: '0102075 | G66: FERRO SILICON MEGNESIUM | H66: KG | I66: RMFL | J66: 47.33 | K66: 4024.23 | X66: 47.33 | Y66: 4024.23 | Z66: =IFERROR((O66+Q66)/(N66+P66),Y66/X66) -> 85.024931
A67: 20300STR | B67: 44287 | C67: 44651 | D67: 20210401 | E67: 20220331 | F67: '0102076 | G67: FERRO SILICON ZIRCONIUM(OBSOL) | H67: KG | I67: RMFL | J67: 44 | K67: 3748.36 | X67: 44 | Y67: 3748.36 | Z67: =IFERROR((O67+Q67)/(N67+P67),Y67/X67) -> 85.19
A68: 20300STR | B68: 44287 | C68: 44651 | D68: 20210401 | E68: 20220331 | F68: '0102084 | G68: FERRO TITANIUM | H68: KG | I68: RMFL | J68: 120.68 | K68: 5930.23 | X68: 120.68 | Y68: 5930.23 | Z68: =IFERROR((O68+Q68)/(N68+P68),Y68/X68) -> 49.140123
A69: 20300STR | B69: 44287 | C69: 44651 | D69: 20210401 | E69: 20220331 | F69: '0102093 | G69: FERRO VANADIUM | H69: KG | I69: RMFL | J69: 40.26 | K69: 79278.29 | N69: -0.78 | O69: -1535.91 | P69: 0.12 | Q69: 236.29 | X69: 39.6 | Y69: 77978.67 | Z69: =IFERROR((O69+Q69)/(N69+P69),Y69/X69) -> 1969.1212
A70: 20300STR | B70: 44287 | C70: 44651 | D70: 20210401 | E70: 20220331 | F70: '0102097 | G70: NITROGENETED FERRO CHROME | H70: KG | I70: RMFL | J70: 45 | K70: 17558.46 | N70: -20.08 | O70: -7835.01 | X70: 24.92 | Y70: 9723.45 | Z70: =IFERROR((O70+Q70)/(N70+P70),Y70/X70) -> 390.18974
A71: 20300STR | B71: 44287 | C71: 44651 | D71: 20210401 | E71: 20220331 | F71: '0102098 | G71: INOKSB2 INNOCULANT | H71: KG | I71: RMFL | L71: 100 | M71: 37500 | N71: -50 | O71: -18750 | X71: 50 | Y71: 18750 | Z71: =IFERROR((O71+Q71)/(N71+P71),Y71/X71) -> 375
A72: 20300STR | B72: 44287 | C72: 44651 | D72: 20210401 | E72: 20220331 | F72: '0102099 | G72: CARBUKAST SUPER | H72: KG | I72: RMFL | J72: 9.04 | K72: 524.32 | X72: 9.04 | Y72: 524.32 | Z72: =IFERROR((O72+Q72)/(N72+P72),Y72/X72) -> 58
A73: 20300STR | B73: 44287 | C73: 44651 | D73: 20210401 | E73: 20220331 | F73: '0104004 | G73: AISI - 310 (RETURNS) | H73: KG | I73: RMFR | J73: 80 | K73: 19095.48 | P73: 1.2 | Q73: 286.44 | X73: 81.2 | Y73: 19381.92 | Z73: =IFERROR((O73+Q73)/(N73+P73),Y73/X73) -> 238.7
A74: 20300STR | B74: 44287 | C74: 44651 | D74: 20210401 | E74: 20220331 | F74: '0104005 | G74: AISI 316L PURCHASE | H74: KG | I74: RMFL | L74: 186049.8 | M74: 48408149 | N74: -186176.67 | O74: -48300441 | P74: 2368.7 | Q74: 587308.4 | R74: -236 | S74: -51442.08 | X74: 2005.83 | Y74: 643574.13 | Z74: =IFERROR((O74+Q74)/(N74+P74),Y74/X74) -> 259.58141
A75: 20300STR | B75: 44287 | C75: 44651 | D75: 20210401 | E75: 20220331 | F75: '0104009 | G75: AISI - 410 ( RETURNS )(CA-15/) | H75: KG | I75: RMFR | J75: 840.4 | K75: 55171.31 | N75: -28616.6 | O75: -1957769.9 | P75: 42702.235 | Q75: 3009662.7 | R75: -9065 | S75: -672351.05 | X75: 5861.035 | Y75: 434713.11 | Z75: =IFERROR((O75+Q75)/(N75+P75),Y75/X75) -> 74.678412
A76: 20300STR | B76: 44287 | C76: 44651 | D76: 20210401 | E76: 20220331 | F76: '0104012 | G76: AISI - 420/CA 40 (RET) | H76: KG | I76: RMFR | J76: 6952 | K76: 214725.52 | N76: -141728.01 | O76: -4633126.3 | P76: 163561.01 | Q76: 5542741.2 | R76: -28785 | S76: -1124342.1 | Y76: -1.72 | Z76: =IFERROR((O76+Q76)/(N76+P76),Y76/X76) -> 41.662385
A77: 20300STR | B77: 44287 | C77: 44651 | D77: 20210401 | E77: 20220331 | F77: '0104013 | G77: AISI - 430 SCRAP | H77: KG | I77: RMFR | J77: 1956.2 | K77: 7138.89 | N77: -260815.92 | O77: -2885665.3 | P77: 291457.2 | Q77: 4140457.8 | R77: -30910 | S77: -1183311.5 | X77: 1687.478 | Y77: 78619.83 | Z77: =IFERROR((O77+Q77)/(N77+P77),Y77/X77) -> 40.951048
A78: 20300STR | B78: 44287 | C78: 44651 | D78: 20210401 | E78: 20220331 | F78: '0104017 | G78: AISI 410 PURE ( PURCHASES ) | H78: KG | I78: RMFL | J78: 6751.1 | K78: 285267.03 | L78: 88385 | M78: 5346380.5 | N78: -95531.95 | O78: -5650133.6 | P78: 581.9 | Q78: 33227.35 | X78: 186.05 | Y78: 14741.26 | Z78: =IFERROR((O78+Q78)/(N78+P78),Y78/X78) -> 59.156433
A79: 20300STR | B79: 44287 | C79: 44651 | D79: 20210401 | E79: 20220331 | F79: '0104019 | G79: MELTING SCRAP OF SS 316 | H79: KG | I79: RMFL | J79: 10414 | K79: 1760362.6 | L79: 54612.45 | M79: 13683613 | N79: -64868.12 | O79: -15442205 | P79: 1000.66 | Q79: 233032.01 | R79: -1135 | S79: -248833.91 | X79: 23.99 | Y79: -14031.93 | Z79: =IFERROR((O79+Q79)/(N79+P79),Y79/X79) -> 238.1365
A80: 20300STR | B80: 44287 | C80: 44651 | D80: 20210401 | E80: 20220331 | F80: '0104021 | G80: AISI - 8615 / 8620 RETURNS | H80: KG | I80: RMFR | J80: 3469.2 | K80: 137996.15 | N80: -29804.466 | O80: -1285263.6 | P80: 36714.828 | Q80: 1613091.5 | R80: -7318 | S80: -322598.77 | X80: 3061.562 | Y80: 143225.28 | Z80: =IFERROR((O80+Q80)/(N80+P80),Y80/X80) -> 47.440047
A81: 20300STR | B81: 44287 | C81: 44651 | D81: 20210401 | E81: 20220331 | F81: '0104031 | G81: 3U5 ASTMA A297 GRH | H81: KG | I81: RMFR | P81: 1.2 | Q81: 24 | X81: 1.2 | Y81: 24 | Z81: =IFERROR((O81+Q81)/(N81+P81),Y81/X81) -> 20
A82: 20300STR | B82: 44287 | C82: 44651 | D82: 20210401 | E82: 20220331 | F82: '0104033 | G82: CA6NM/HY19593VAR/RW2/DIN1.7445 | H82: KG | I82: RMFR | N82: -152 | O82: -14591.3 | P82: 1442.8 | Q82: 138502.16 | X82: 1290.8 | Y82: 123910.86 | Z82: =IFERROR((O82+Q82)/(N82+P82),Y82/X82) -> 95.995398
A83: 20300STR | B83: 44287 | C83: 44651 | D83: 20210401 | E83: 20220331 | F83: '0104042 | G83: BS 3146 CLA 12 A | H83: KG | I83: RMFR | K83: 0.12 | Y83: 0.12 | Z83: =IFERROR((O83+Q83)/(N83+P83),Y83/X83) -> #DIV/0!
A84: 20300STR | B84: 44287 | C84: 44651 | D84: 20210401 | E84: 20220331 | F84: '0104047 | G84: PIG IRON GRADE-FG-25 GRADE | H84: KG | I84: RMFL | J84: 2312.2 | K84: 99424.6 | N84: -2312 | O84: -99416 | X84: 0.2 | Y84: 8.6 | Z84: =IFERROR((O84+Q84)/(N84+P84),Y84/X84) -> 43
A85: 20300STR | B85: 44287 | C85: 44651 | D85: 20210401 | E85: 20220331 | F85: '0104050 | G85: EN 19 / DIN 1.7218 | H85: KG | I85: RMFR | J85: 354.2 | K85: 12312.92 | N85: -2204.6 | O85: -76637.34 | P85: 3066.8 | Q85: 112871.11 | X85: 1216.4 | Y85: 48546.69 | Z85: =IFERROR((O85+Q85)/(N85+P85),Y85/X85) -> 42.024785
A86: 20300STR | B86: 44287 | C86: 44651 | D86: 20210401 | E86: 20220331 | F86: '0104051 | G86: CAST IRON (RETURNS) | H86: KG | I86: RMFR | J86: 1186 | K86: 83779.34 | N86: -8977.6 | O86: -634180.39 | P86: 11599.7 | Q86: 819406.22 | R86: -1900 | S86: -134216.57 | X86: 1908.1 | Y86: 134788.6 | Z86: =IFERROR((O86+Q86)/(N86+P86),Y86/X86) -> 70.640262
A87: 20300STR | B87: 44287 | C87: 44651 | D87: 20210401 | E87: 20220331 | F87: '0104052 | G87: CAST IRON SPL. ALLOY(4B2 RET.) | H87: KG | I87: RMFR | P87: 0.2 | Q87: 28.7 | X87: 0.2 | Y87: 28.7 | Z87: =IFERROR((O87+Q87)/(N87+P87),Y87/X87) -> 143.5
A88: 20300STR | B88: 44287 | C88: 44651 | D88: 20210401 | E88: 20220331 | F88: '0104055 | G88: CD 4 MCU | H88: KG | I88: RMFR | J88: 93 | K88: 19272.5 | P88: 10.214 | Q88: 2116.66 | X88: 103.214 | Y88: 21389.16 | Z88: =IFERROR((O88+Q88)/(N88+P88),Y88/X88) -> 207.23125
A89: 20300STR | B89: 44287 | C89: 44651 | D89: 20210401 | E89: 20220331 | F89: '0104057 | G89: CF 3M | H89: KG | I89: RMFR | J89: 8007.2 | K89: 1475416.4 | N89: -513818.93 | O89: -94150897 | P89: 527275.88 | Q89: 96616580 | V89: -15373.47 | W89: -2833076.9 | X89: 6090.679 | Y89: 1108023.2 | Z89: =IFERROR((O89+Q89)/(N89+P89),Y89/X89) -> 183.22754
A90: 20300STR | B90: 44287 | C90: 44651 | D90: 20210401 | E90: 20220331 | F90: '0104058 | G90: CF-8 PURCHASE | H90: KG | I90: RMFL | J90: 3494.4 | K90: 421133.8 | L90: 189225 | M90: 33496060 | N90: -178556.65 | O90: -31532846 | P90: 630.4 | Q90: 108414.48 | R90: -14192 | S90: -2407905.4 | X90: 601.15 | Y90: 84856.44 | Z90: =IFERROR((O90+Q90)/(N90+P90),Y90/X90) -> 176.61493
A91: 20300STR | B91: 44287 | C91: 44651 | D91: 20210401 | E91: 20220331 | F91: '0104059 | G91: CF8 SCRAP ( RETURNS ) | H91: KG | I91: RMFR | J91: 755 | K91: 99308.13 | N91: -284252.77 | O91: -36907133 | P91: 296402.93 | Q91: 38443442 | X91: 12905.167 | Y91: 1635617.5 | Z91: =IFERROR((O91+Q91)/(N91+P91),Y91/X91) -> 126.44347
A92: 20300STR | B92: 44287 | C92: 44651 | D92: 20210401 | E92: 20220331 | F92: '0104060 | G92: CF8M (AISI 316L RETURNS) | H92: KG | I92: RMFR | J92: 13771.1 | K92: 2091046 | N92: -158490.19 | O92: -24295857 | P92: 169375.99 | Q92: 25983402 | R92: -210 | S92: -31887.43 | V92: -14744 | W92: -2238801.2 | X92: 9702.901 | Y92: 1507902.4 | Z92: =IFERROR((O92+Q92)/(N92+P92),Y92/X92) -> 155.02259
A93: 20300STR | B93: 44287 | C93: 44651 | D93: 20210401 | E93: 20220331 | F93: '0104068 | G93: DIN-1.4581 | H93: KG | I93: RMFR | J93: 1806.2 | K93: 324074.77 | N93: -14754.34 | O93: -2614475.8 | P93: 15457.1 | Q93: 2730880 | X93: 2508.96 | Y93: 440478.98 | Z93: =IFERROR((O93+Q93)/(N93+P93),Y93/X93) -> 165.63864
A94: 20300STR | B94: 44287 | C94: 44651 | D94: 20210401 | E94: 20220331 | F94: '0104075 | G94: DIN 1.4460 (7U76) RETURNS | H94: KG | I94: RMFR | K94: 9.79 | Y94: 9.79 | Z94: =IFERROR((O94+Q94)/(N94+P94),Y94/X94) -> #DIV/0!
A95: 20300STR | B95: 44287 | C95: 44651 | D95: 20210401 | E95: 20220331 | F95: '0104077 | G95: EN 3A SCRAP RETURNS (W.C.B.) | H95: KG | I95: RMFR | N95: -4011.4 | O95: -145647.45 | P95: 8409.89 | Q95: 310326.88 | R95: -3594 | S95: -134559.36 | X95: 804.49 | Y95: 30120.07 | Z95: =IFERROR((O95+Q95)/(N95+P95),Y95/X95) -> 37.439992
A96: 20300STR | B96: 44287 | C96: 44651 | D96: 20210401 | E96: 20220331 | F96: '0104079 | G96: EN 8 | H96: KG | I96: RMFR | K96: 0.17 | Y96: 0.17 | Z96: =IFERROR((O96+Q96)/(N96+P96),Y96/X96) -> #DIV/0!
A97: 20300STR | B97: 44287 | C97: 44651 | D97: 20210401 | E97: 20220331 | F97: '0104080 | G97: EN 9 | H97: KG | I97: RMFR | J97: 2868.8 | K97: 81444.32 | N97: -56429.09 | O97: -1790577.9 | P97: 69900.801 | Q97: 2259784.9 | R97: -16010 | S97: -538242.97 | X97: 330.511 | Y97: 12408.39 | Z97: =IFERROR((O97+Q97)/(N97+P97),Y97/X97) -> 34.829061
A98: 20300STR | B98: 44287 | C98: 44651 | D98: 20210401 | E98: 20220331 | F98: '0104082 | G98: DIN 1.7225 (7U128) | H98: KG | I98: RMFR | J98: 112 | K98: 4080.38 | N98: -2506.58 | O98: -91360.49 | P98: 4936.794 | Q98: 181873.28 | R98: -2463 | S98: -91367.99 | X98: 79.214 | Y98: 3225.18 | Z98: =IFERROR((O98+Q98)/(N98+P98),Y98/X98) -> 37.244782
A99: 20300STR | B99: 44287 | C99: 44651 | D99: 20210401 | E99: 20220331 | F99: '0104098 | G99: DIN 1.4112 | H99: KG | I99: RMFR | N99: -11 | O99: -315.77 | P99: 11.2 | Q99: 321.51 | X99: 0.2 | Y99: 5.74 | Z99: =IFERROR((O99+Q99)/(N99+P99),Y99/X99) -> 28.7
A100: 20300STR | B100: 44287 | C100: 44651 | D100: 20210401 | E100: 20220331 | F100: '0104099 | G100: DIN 1.4057 | H100: KG | I100: RMFR | J100: 581.58 | K100: 53282.11 | N100: -581.64 | O100: -37482.86 | P100: 581.7 | Q100: 52083.85 | X100: 581.64 | Y100: 67883.1 | Z100: =IFERROR((O100+Q100)/(N100+P100),Y100/X100) -> 243349.83
...

Sheet Mn Ledger
I1: B/p GL | J1: Opening Stock | K1: Opening Stock | L1: RECEIPT | M1: RECEIPT | N1: SIR | O1: SIR | P1: IGR | Q1: IGR | R1: SALES | S1: SALES | T1: TRASNFER | U1: TRASNFER | V1: Other Tran | W1: Other Tran | X1: Closing Stock | Y1: Closing Stock
A2: Branch Plant | B2: From Date | C2: To Date | D2: From Date | E2: To Date | F2: Item Code | G2: Description | H2: UOM | I2: Code | J2: Qty | K2: Amount | L2: Qty | M2: Amount | N2: Qty | O2: Amount | P2: Qty | Q2: Amount | R2: Qty | S2: Amount | T2: Qty | U2: Amount | V2: Qty | W2: Amount | X2: Qty | Y2: Amount | Z2: Rate
A3: 20200STR | B3: 44287 | C3: 44651 | D3: 20210401 | E3: 20220331 | F3: '001T0128D | G3: 1T128 FOUR CAVITY WAX INJ. | H3: NO | I3: TLL | L3: 1 | M3: 70000 | N3: -1 | O3: -70000 | Z3: =IFERROR((O3+Q3)/(N3+P3),Y3/X3) -> 70000
A4: 20200STR | B4: 44287 | C4: 44651 | D4: 20210401 | E4: 20220331 | F4: '001T0155D | G4: 1T155 FOUR CAVITY WAX INJE. | H4: NO | I4: TLL | L4: 1 | M4: 110000 | N4: -1 | O4: -110000 | Z4: =IFERROR((O4+Q4)/(N4+P4),Y4/X4) -> 110000
A5: 20200STR | B5: 44287 | C5: 44651 | D5: 20210401 | E5: 20220331 | F5: '001T0156D | G5: 1T156 FOUR CAVITY WAX MOULD | H5: NO | I5: TLL | L5: 1 | M5: 80000 | N5: -1 | O5: -80000 | Z5: =IFERROR((O5+Q5)/(N5+P5),Y5/X5) -> 80000
A6: 20200STR | B6: 44287 | C6: 44651 | D6: 20210401 | E6: 20220331 | F6: '001T0162D | G6: 1T162 FOUR CAVITY WAX INJE. | H6: NO | I6: TLL | L6: 1 | M6: 1 | N6: -1 | O6: -1 | P6: 1 | Q6: 110000 | R6: -1 | S6: -110000 | Z6: =IFERROR((O6+Q6)/(N6+P6),Y6/X6) -> #DIV/0!
A7: 20200STR | B7: 44287 | C7: 44651 | D7: 20210401 | E7: 20220331 | F7: '001T0165D | G7: 1T165/138 TWO CAVITY WAX INJ. | H7: NO | I7: TLL | L7: 1 | M7: 80000 | N7: -1 | O7: -80000 | Z7: =IFERROR((O7+Q7)/(N7+P7),Y7/X7) -> 80000
A8: 20200STR | B8: 44287 | C8: 44651 | D8: 20210401 | E8: 20220331 | F8: '001T0199D | G8: 1T199 TWO CAVITY WAX INJECTION | H8: NO | I8: TLL | L8: 1 | M8: 120000 | N8: -1 | O8: -120000 | Z8: =IFERROR((O8+Q8)/(N8+P8),Y8/X8) -> 120000
A9: 20200STR | B9: 44287 | C9: 44651 | D9: 20210401 | E9: 20220331 | F9: '001T0200D | G9: 1T200 TWO CAVITY WAX INJ. DIE | H9: NO | I9: TLL | L9: 1 | M9: 120000 | N9: -1 | O9: -120000 | Z9: =IFERROR((O9+Q9)/(N9+P9),Y9/X9) -> 120000
A10: 20200STR | B10: 44287 | C10: 44651 | D10: 20210401 | E10: 20220331 | F10: '001T0203D | G10: 1T203 TWO CAVITY WAX INJECTION | H10: NO | I10: TLL | L10: 1 | M10: 1 | N10: -1 | O10: -1 | Z10: =IFERROR((O10+Q10)/(N10+P10),Y10/X10) -> 1
A11: 20200STR | B11: 44287 | C11: 44651 | D11: 20210401 | E11: 20220331 | F11: '001T0204D | G11: 1T204 TWO CAVITY WAX INJECTION | H11: NO | I11: TLL | L11: 1 | M11: 1 | N11: -1 | O11: -1 | Z11: =IFERROR((O11+Q11)/(N11+P11),Y11/X11) -> 1
A12: 20200STR | B12: 44287 | C12: 44651 | D12: 20210401 | E12: 20220331 | F12: '001T0205D | G12: 1T205 TWO CAVITY WAX INJECTION | H12: NO | I12: TLL | L12: 1 | M12: 1 | N12: -1 | O12: -1 | Z12: =IFERROR((O12+Q12)/(N12+P12),Y12/X12) -> 1
A13: 20200STR | B13: 44287 | C13: 44651 | D13: 20210401 | E13: 20220331 | F13: '001T0210D | G13: 1T210 SINGLE CAVITY WAX INJ. | H13: NO | I13: TLL | L13: 1 | M13: 140000 | N13: -1 | O13: -140000 | Z13: =IFERROR((O13+Q13)/(N13+P13),Y13/X13) -> 140000
A14: 20200STR | B14: 44287 | C14: 44651 | D14: 20210401 | E14: 20220331 | F14: '001T0210RD | G14: 1T210 RISER MOULD WITH | H14: NO | I14: TLL | L14: 1 | M14: 50000 | N14: -1 | O14: -50000 | Z14: =IFERROR((O14+Q14)/(N14+P14),Y14/X14) -> 50000
A15: 20200STR | B15: 44287 | C15: 44651 | D15: 20210401 | E15: 20220331 | F15: '001T0213D | G15: 1T213 TWO CAVITY WAX INJECTION | H15: NO | I15: TLL | L15: 1 | M15: 1 | N15: -1 | O15: -1 | Z15: =IFERROR((O15+Q15)/(N15+P15),Y15/X15) -> 1
A16: 20200STR | B16: 44287 | C16: 44651 | D16: 20210401 | E16: 20220331 | F16: '001T0214D | G16: 1T214 TWO CAVITY WAX INJECTION | H16: NO | I16: TLL | L16: 1 | M16: 90000 | N16: -1 | O16: -90000 | Z16: =IFERROR((O16+Q16)/(N16+P16),Y16/X16) -> 90000
A17: 20200STR | B17: 44287 | C17: 44651 | D17: 20210401 | E17: 20220331 | F17: '002T0040D | G17: 2T40 MAIN DIE | H17: NO | I17: TLL | L17: 1 | M17: 80000 | N17: -1 | O17: -80000 | Z17: =IFERROR((O17+Q17)/(N17+P17),Y17/X17) -> 80000
A18: 20200STR | B18: 44287 | C18: 44651 | D18: 20210401 | E18: 20220331 | F18: '002T0052D | G18: 2T52 TWO CAVITY WAX MOULD | H18: NO | I18: TLL | L18: 1 | M18: 70000 | N18: -1 | O18: -70000 | Z18: =IFERROR((O18+Q18)/(N18+P18),Y18/X18) -> 70000
... A27: 20200STR | B27: 44287 | C27: 44651 | D27: 20210401 | E27: 20220331 | F27: '007U0599D | G27: 7U599 TWO CAVITY WAX INJECTION | H27: NO | I27: TLL | L27: 1 | M27: 1 | N27: -1 | O27: -1 | Z27: =IFERROR((O27+Q27)/(N27+P27),Y27/X27) -> 1
A28: 20200STR | B28: 44287 | C28: 44651 | D28: 20210401 | E28: 20220331 | F28: '0101001 | G28: ALUMINIUM PLATES & FLATS | H28: KG | I28: RMTL | J28: 11.5 | K28: 3449.64 | P28: 0.39 | Q28: 116.99 | X28: 11.89 | Y28: 3566.63 | Z28: =IFERROR((O28+Q28)/(N28+P28),Y28/X28) -> 299.97436
A29: 20200STR | B29: 44287 | C29: 44651 | D29: 20210401 | E29: 20220331 | F29: '0101002 | G29: ALUMINIUM SCRAP | H29: KG | I29: RMFL | J29: 76.3 | K29: 12566.59 | L29: 1105 | M29: 236494.75 | N29: -1391.07 | O29: -296951.27 | P29: 211.855 | Q29: 48449.6 | X29: 2.085 | Y29: 559.67 | Z29: =IFERROR((O29+Q29)/(N29+P29),Y29/X29) -> 210.73483
A30: 20200STR | B30: 44287 | C30: 44651 | D30: 20210401 | E30: 20220331 | F30: '0101013 | G30: CHROMIUM ( INDIGENOUS ) | H30: KG | I30: RMFL | J30: 4.65 | K30: 4464 | X30: 4.65 | Y30: 4464 | Z30: =IFERROR((O30+Q30)/(N30+P30),Y30/X30) -> 960
A31: 20200STR | B31: 44287 | C31: 44651 | D31: 20210401 | E31: 20220331 | F31: '0101017 | G31: COPPER SCRAP ( RETURNS ) | H31: KG | I31: RMFR | J31: 930 | K31: 121727.71 | P31: 19.44 | Q31: 2544.5 | R31: -934 | S31: -122251.26 | X31: 15.44 | Y31: 2020.95 | Z31: =IFERROR((O31+Q31)/(N31+P31),Y31/X31) -> 130.88992
A32: 20200STR | B32: 44287 | C32: 44651 | D32: 20210401 | E32: 20220331 | F32: '0101018 | G32: CUPRO MANG INGOTS 70:30(P&R) | H32: KG | I32: RMFL | J32: 28.4 | K32: 2942.8 | X32: 28.4 | Y32: 2942.8 | Z32: =IFERROR((O32+Q32)/(N32+P32),Y32/X32) -> 103.61972
A33: 20200STR | B33: 44287 | C33: 44651 | D33: 20210401 | E33: 20220331 | F33: '0101021 | G33: FERRO SILICO CALCIUM | H33: KG | I33: RMFL | J33: 144 | K33: 19185.76 | L33: 3794 | M33: 1004339.8 | N33: -3976.56 | O33: -1019941.7 | P33: 116.06 | Q33: 21959.44 | X33: 77.5 | Y33: 25543.35 | Z33: =IFERROR((O33+Q33)/(N33+P33),Y33/X33) -> 258.51114
A34: 20200STR | B34: 44287 | C34: 44651 | D34: 20210401 | E34: 20220331 | F34: '0101066 | G34: NICKEL BRIQUTTIES LOCAL | H34: KG | I34: RMFL | J34: 672.145 | K34: 881156.44 | L34: 2330 | M34: 3450714.6 | N34: -3059.21 | O34: -4413069.4 | P34: 55.455 | Q34: 83241.37 | V34: 40 | W34: 68146.21 | X34: 38.39 | Y34: 70189.29 | Z34: =IFERROR((O34+Q34)/(N34+P34),Y34/X34) -> 1441.4718
A35: 20200STR | B35: 44287 | C35: 44651 | D35: 20210401 | E35: 20220331 | F35: '0101068 | G35: NICKEL 4"X4" | H35: KG | I35: RMFL | L35: 100 | M35: 167500 | N35: -100 | O35: -167500.01 | Y35: -0.01 | Z35: =IFERROR((O35+Q35)/(N35+P35),Y35/X35) -> 1675.0001
A36: 20200STR | B36: 44287 | C36: 44651 | D36: 20210401 | E36: 20220331 | F36: '0101071 | G36: NICKEL CATHODE 1"X1" SQUARE | H36: KG | I36: RMFL | L36: 740 | M36: 1230101.3 | N36: -700.81 | O36: -1169849.5 | P36: 0.81 | Q36: 1346.1 | V36: -40 | W36: -61597.92 | Y36: -0.04 | Z36: =IFERROR((O36+Q36)/(N36+P36),Y36/X36) -> 1669.2906
A37: 20200STR | B37: 44287 | C37: 44651 | D37: 20210401 | E37: 20220331 | F37: '0101093 | G37: PURE TUNGSTON | H37: KG | I37: RMFL | J37: 4.31 | K37: 9427.7 | X37: 4.31 | Y37: 9427.7 | Z37: =IFERROR((O37+Q37)/(N37+P37),Y37/X37) -> 2187.4014
A38: 20200STR | B38: 44287 | C38: 44651 | D38: 20210401 | E38: 20220331 | F38: '0101094 | G38: TUNGSTON CARBIDE SCRAP | H38: KG | I38: RMFL | J38: 91 | K38: 10373.94 | X38: 91 | Y38: 10373.94 | Z38: =IFERROR((O38+Q38)/(N38+P38),Y38/X38) -> 113.99934
A39: 20200STR | B39: 44287 | C39: 44651 | D39: 20210401 | E39: 20220331 | F39: '0101187 | G39: ALUMINIUM PLATE | H39: KG | I39: STSL | L39: 27 | M39: 9450 | N39: -27 | O39: -9450 | Z39: =IFERROR((O39+Q39)/(N39+P39),Y39/X39) -> 350
A40: 20200STR | B40: 44287 | C40: 44651 | D40: 20210401 | E40: 20220331 | F40: '0102017 | G40: FERRO CHROME L.C. 0.1C | H40: KG | I40: RMFL | J40: 1538.18 | K40: 256001.9 | L40: 10537 | M40: 2475382.5 | N40: -11594.31 | O40: -2580553.5 | P40: 132.955 | Q40: 25167.32 | R40: -1 | S40: -172.54 | X40: 612.825 | Y40: 175825.64 | Z40: =IFERROR((O40+Q40)/(N40+P40),Y40/X40) -> 222.95673
A41: 20200STR | B41: 44287 | C41: 44651 | D41: 20210401 | E41: 20220331 | F41: '0102034 | G41: IRON SULPHIDE | H41: KG | I41: RMFL | J41: 46.6 | K41: 1431.82 | L41: 133 | M41: 4209.04 | N41: -155.4 | O41: -4920.92 | P41: 0.72 | Q41: 22.48 | R41: -1 | S41: -34.81 | X41: 23.92 | Y41: 707.61 | Z41: =IFERROR((O41+Q41)/(N41+P41),Y41/X41) -> 31.668218
A42: 20200STR | B42: 44287 | C42: 44651 | D42: 20210401 | E42: 20220331 | F42: '0102045 | G42: SILICO MN | H42: KG | I42: RMFL | J42: 92.99 | K42: 5872.22 | L42: 3850 | M42: 368450 | N42: -3960.066 | O42: -375767.5 | P42: 41.85 | Q42: 3685.79 | X42: 24.774 | Y42: 2240.51 | Z42: =IFERROR((O42+Q42)/(N42+P42),Y42/X42) -> 94.962021
A43: 20200STR | B43: 44287 | C43: 44651 | D43: 20210401 | E43: 20220331 | F43: '0102048 | G43: FERRO MOLYBDENUM | H43: KG | I43: RMFL | J43: 183.218 | K43: 249411.84 | L43: 745 | M43: 1450946.2 | N43: -918.773 | O43: -1665109.9 | P43: 9.937 | Q43: 16850.27 | X43: 19.382 | Y43: 52098.43 | Z43: =IFERROR((O43+Q43)/(N43+P43),Y43/X43) -> 1813.5941
A44: 20200STR | B44: 44287 | C44: 44651 | D44: 20210401 | E44: 20220331 | F44: '0102049 | G44: HIGH CARBON FERRO MANGANES | H44: KG | I44: RMFL | J44: 300.526 | K44: 18922.12 | L44: 6050 | M44: 603400 | N44: -6047.806 | O44: -592072.39 | P44: 105.85 | Q44: 11485.62 | R44: -150 | S44: -15252.64 | X44: 258.57 | Y44: 26482.71 | Z44: =IFERROR((O44+Q44)/(N44+P44),Y44/X44) -> 97.709705
A45: 20200STR | B45: 44287 | C45: 44651 | D45: 20210401 | E45: 20220331 | F45: '0102074 | G45: FERRO SILICON | H45: KG | I45: RMFL | J45: 468.705 | K45: 51936.72 | L45: 5117 | M45: 868840.99 | N45: -5603.43 | O45: -923038.63 | P45: 104.225 | Q45: 21148.07 | X45: 86.5 | Y45: 18887.15 | Z45: =IFERROR((O45+Q45)/(N45+P45),Y45/X45) -> 164.00381
A46: 20200STR | B46: 44287 | C46: 44651 | D46: 20210401 | E46: 20220331 | F46: '0102084 | G46: FERRO TITANIUM | H46: KG | I46: RMFL | J46: 24.8 | K46: 1543.3 | X46: 24.8 | Y46: 1543.3 | Z46: =IFERROR((O46+Q46)/(N46+P46),Y46/X46) -> 62.229839
A47: 20200STR | B47: 44287 | C47: 44651 | D47: 20210401 | E47: 20220331 | F47: '0102088 | G47: TUNGSTON NICKEL (PUR. & RET.) | H47: KG | I47: RMFL | J47: 68.5 | K47: 115418.39 | N47: -61.6 | O47: -104839.36 | X47: 6.9 | Y47: 10579.03 | Z47: =IFERROR((O47+Q47)/(N47+P47),Y47/X47) -> 1701.9377
A48: 20200STR | B48: 44287 | C48: 44651 | D48: 20210401 | E48: 20220331 | F48: '0102093 | G48: FERRO VANADIUM | H48: KG | I48: RMFL | J48: 0.17 | K48: 330.98 | X48: 0.17 | Y48: 330.98 | Z48: =IFERROR((O48+Q48)/(N48+P48),Y48/X48) -> 1946.9412
A49: 20200STR | B49: 44287 | C49: 44651 | D49: 20210401 | E49: 20220331 | F49: '0102095 | G49: PH COPPER | H49: KG | I49: RMFL | J49: 2.5 | K49: 516.35 | X49: 2.5 | Y49: 516.35 | Z49: =IFERROR((O49+Q49)/(N49+P49),Y49/X49) -> 206.54
A50: 20200STR | B50: 44287 | C50: 44651 | D50: 20210401 | E50: 20220331 | F50: '0103025 | G50: COBALT BASE ALLOYS SCRAP | H50: KG | I50: RMFL | J50: 194 | K50: 138172.62 | R50: -193 | S50: -137460.39 | X50: 1 | Y50: 712.23 | Z50: =IFERROR((O50+Q50)/(N50+P50),Y50/X50) -> 712.23
A51: 20200STR | B51: 44287 | C51: 44651 | D51: 20210401 | E51: 20220331 | F51: '0103065 | G51: MANGANESE BRONZ INGOT (RETURN) | H51: KG | I51: RMFR | J51: 9.57 | K51: 2654.57 | N51: -3334.073 | O51: -924805.19 | P51: 3504.022 | Q51: 971945.62 | X51: 179.519 | Y51: 49795 | Z51: =IFERROR((O51+Q51)/(N51+P51),Y51/X51) -> 277.37986
A52: 20200STR | B52: 44287 | C52: 44651 | D52: 20210401 | E52: 20220331 | F52: '0103066 | G52: MANGANESE BRONZE HTB-1(INGOTS | H52: KG | I52: RMFL | J52: 200 | K52: 102000 | L52: 2440 | M52: 1328259.8 | N52: -2344.13 | O52: -1263206.4 | P52: 22 | Q52: 11770 | X52: 317.87 | Y52: 178823.43 | Z52: =IFERROR((O52+Q52)/(N52+P52),Y52/X52) -> 538.91745
A53: 20200STR | B53: 44287 | C53: 44651 | D53: 20210401 | E53: 20220331 | F53: '0103068 | G53: MN BZ HTB-3 (PURCHASE) | H53: KG | I53: RMFL | J53: 169 | K53: 57460 | X53: 169 | Y53: 57460 | Z53: =IFERROR((O53+Q53)/(N53+P53),Y53/X53) -> 340
A54: 20200STR | B54: 44287 | C54: 44651 | D54: 20210401 | E54: 20220331 | F54: '0103070 | G54: MN.BZ. HTB-3 RETURN | H54: KG | I54: RMFR | J54: 571 | K54: 165019 | X54: 571 | Y54: 165019 | Z54: =IFERROR((O54+Q54)/(N54+P54),Y54/X54) -> 289
A55: 20200STR | B55: 44287 | C55: 44651 | D55: 20210401 | E55: 20220331 | F55: '0103071 | G55: BRASS CUT PCS USED SCRAP | H55: KG | I55: RMFR | J55: 96 | K55: 5764.19 | P55: 10 | Q55: 600.44 | X55: 106 | Y55: 6364.63 | Z55: =IFERROR((O55+Q55)/(N55+P55),Y55/X55) -> 60.044
A56: 20200STR | B56: 44287 | C56: 44651 | D56: 20210401 | E56: 20220331 | F56: '0104004 | G56: AISI - 310 (RETURNS) | H56: KG | I56: RMFR | N56: -1556 | O56: -517116.09 | P56: 1879 | Q56: 676652.2 | X56: 323 | Y56: 159536.11 | Z56: =IFERROR((O56+Q56)/(N56+P56),Y56/X56) -> 493.91985
A57: 20200STR | B57: 44287 | C57: 44651 | D57: 20210401 | E57: 20220331 | F57: '0104005 | G57: AISI 316L PURCHASE | H57: KG | I57: RMFL | L57: 236 | M57: 51442.08 | N57: -236 | O57: -51442.09 | Y57: -0.01 | Z57: =IFERROR((O57+Q57)/(N57+P57),Y57/X57) -> 217.97496
A58: 20200STR | B58: 44287 | C58: 44651 | D58: 20210401 | E58: 20220331 | F58: '0104009 | G58: AISI - 410 ( RETURNS )(CA-15/) | H58: KG | I58: RMFR | J58: 2540 | K58: 35887.83 | N58: -4904.225 | O58: -245911.7 | P58: 3913.45 | Q58: 407087.82 | X58: 1549.225 | Y58: 197063.95 | Z58: =IFERROR((O58+Q58)/(N58+P58),Y58/X58) -> -162.67681
A59: 20200STR | B59: 44287 | C59: 44651 | D59: 20210401 | E59: 20220331 | F59: '0104012 | G59: AISI - 420/CA 40 (RET) | H59: KG | I59: RMFR | J59: 3472.3 | K59: 73166.35 | N59: -36215.582 | O59: -809471.67 | P59: 39561.264 | Q59: 943544.58 | X59: 6817.982 | Y59: 207239.26 | Z59: =IFERROR((O59+Q59)/(N59+P59),Y59/X59) -> 40.073417
A60: 20200STR | B60: 44287 | C60: 44651 | D60: 20210401 | E60: 20220331 | F60: '0104013 | G60: AISI - 430 SCRAP | H60: KG | I60: RMFR | J60: 17.2 | K60: 927.47 | L60: 5980 | M60: 21822.81 | N60: -195535.1 | O60: -7846669.4 | P60: 201871.26 | Q60: 8629945.1 | X60: 12333.36 | Y60: 806026 | Z60: =IFERROR((O60+Q60)/(N60+P60),Y60/X60) -> 123.61994
A61: 20200STR | B61: 44287 | C61: 44651 | D61: 20210401 | E61: 20220331 | F61: '0104019 | G61: MELTING SCRAP OF SS 316 | H61: KG | I61: RMFL | J61: 115.222 | K61: 19718.04 | L61: 1135 | M61: 248833.91 | N61: -1072.28 | O61: -226896.07 | P61: 34.5 | Q61: 5901.54 | X61: 212.442 | Y61: 47557.42 | Z61: =IFERROR((O61+Q61)/(N61+P61),Y61/X61) -> 212.94931
A62: 20200STR | B62: 44287 | C62: 44651 | D62: 20210401 | E62: 20220331 | F62: '0104021 | G62: AISI - 8615 / 8620 RETURNS | H62: KG | I62: RMFR | J62: 15828.3 | K62: 705589.84 | N62: -204924.82 | O62: -9179839.5 | P62: 217296.84 | Q62: 9763383 | X62: 28200.32 | Y62: 1289133.4 | Z62: =IFERROR((O62+Q62)/(N62+P62),Y62/X62) -> 47.166391
A63: 20200STR | B63: 44287 | C63: 44651 | D63: 20210401 | E63: 20220331 | F63: '0104043 | G63: BS 3146 CLA 13 | H63: KG | I63: RMFR | J63: 311 | K63: 65839.34 | N63: -24 | O63: -5080.85 | P63: 39 | Q63: 8256.38 | X63: 326 | Y63: 69014.87 | Z63: =IFERROR((O63+Q63)/(N63+P63),Y63/X63) -> 211.702
A64: 20200STR | B64: 44287 | C64: 44651 | D64: 20210401 | E64: 20220331 | F64: '0104051 | G64: CAST IRON (RETURNS) | H64: KG | I64: RMFR | J64: 2320 | K64: 19557.6 | X64: 2320 | Y64: 19557.6 | Z64: =IFERROR((O64+Q64)/(N64+P64),Y64/X64) -> 8.43
A65: 20200STR | B65: 44287 | C65: 44651 | D65: 20210401 | E65: 20220331 | F65: '0104057 | G65: CF 3M | H65: KG | I65: RMFR | J65: 93 | K65: 16918.1 | P65: 1393.784 | Q65: 253549.94 | X65: 1486.784 | Y65: 270468.04 | Z65: =IFERROR((O65+Q65)/(N65+P65),Y65/X65) -> 181.9148
A66: 20200STR | B66: 44287 | C66: 44651 | D66: 20210401 | E66: 20220331 | F66: '0104058 | G66: CF-8 PURCHASE | H66: KG | I66: RMFL | J66: 1204 | K66: 141019.99 | L66: 14192 | M66: 2407905.4 | N66: -14778.99 | O66: -2484823.5 | P66: 315 | Q66: 48328.28 | R66: -900 | S66: -106274.61 | X66: 32.01 | Y66: 6155.57 | Z66: =IFERROR((O66+Q66)/(N66+P66),Y66/X66) -> 168.4525
A67: 20200STR | B67: 44287 | C67: 44651 | D67: 20210401 | E67: 20220331 | F67: '0104059 | G67: CF8 SCRAP ( RETURNS ) | H67: KG | I67: RMFR | J67: 208.6 | K67: 29493.44 | N67: -3967.835 | O67: -525211.29 | P67: 4017.46 | Q67: 527069.72 | X67: 258.225 | Y67: 31351.87 | Z67: =IFERROR((O67+Q67)/(N67+P67),Y67/X67) -> 37.449471
A68: 20200STR | B68: 44287 | C68: 44651 | D68: 20210401 | E68: 20220331 | F68: '0104060 | G68: CF8M (AISI 316L RETURNS) | H68: KG | I68: RMFR | J68: 265 | K68: 37658.36 | N68: -1448.516 | O68: -209380.97 | P68: 1460.532 | Q68: 214506.82 | X68: 277.016 | Y68: 42784.21 | Z68: =IFERROR((O68+Q68)/(N68+P68),Y68/X68) -> 426.58539
A69: 20200STR | B69: 44287 | C69: 44651 | D69: 20210401 | E69: 20220331 | F69: '0104068 | G69: DIN-1.4581 | H69: KG | I69: RMFR | P69: 118.43 | Q69: 17798.85 | X69: 118.43 | Y69: 17798.85 | Z69: =IFERROR((O69+Q69)/(N69+P69),Y69/X69) -> 150.29004
A70: 20200STR | B70: 44287 | C70: 44651 | D70: 20210401 | E70: 20220331 | F70: '0104071 | G70: DTD 5299 | H70: KG | I70: RMFR | P70: 0.48 | X70: 0.48 | Z70: =IFERROR((O70+Q70)/(N70+P70),Y70/X70) -> 0
A71: 20200STR | B71: 44287 | C71: 44651 | D71: 20210401 | E71: 20220331 | F71: '0104074 | G71: DIN 1.4138 | H71: KG | I71: RMFR | P71: 66 | X71: 66 | Z71: =IFERROR((O71+Q71)/(N71+P71),Y71/X71) -> 0
A72: 20200STR | B72: 44287 | C72: 44651 | D72: 20210401 | E72: 20220331 | F72: '0104077 | G72: EN 3A SCRAP RETURNS (W.C.B.) | H72: KG | I72: RMFR | J72: 939 | K72: 35221.33 | N72: -30270.846 | O72: -1144992.1 | P72: 33124.492 | Q72: 1255164.7 | X72: 3792.646 | Y72: 145393.94 | Z72: =IFERROR((O72+Q72)/(N72+P72),Y72/X72) -> 38.607665
A73: 20200STR | B73: 44287 | C73: 44651 | D73: 20210401 | E73: 20220331 | F73: '0104079 | G73: EN 8 | H73: KG | I73: RMFR | J73: 1849 | K73: 69456.86 | N73: -142394.5 | O73: -5466968.8 | P73: 143054.39 | Q73: 5495521.5 | X73: 2508.883 | Y73: 98009.54 | Z73: =IFERROR((O73+Q73)/(N73+P73),Y73/X73) -> 43.269307
A74: 20200STR | B74: 44287 | C74: 44651 | D74: 20210401 | E74: 20220331 | F74: '0104080 | G74: EN 9 | H74: KG | I74: RMFR | J74: 692 | K74: 24336.43 | N74: -100030.27 | O74: -3551767.2 | P74: 100384.14 | Q74: 3565322.5 | V74: -210 | W74: -7569.58 | X74: 835.872 | Y74: 30322.16 | Z74: =IFERROR((O74+Q74)/(N74+P74),Y74/X74) -> 38.305687
A75: 20200STR | B75: 44287 | C75: 44651 | D75: 20210401 | E75: 20220331 | F75: '0104084 | G75: EN 24 SCRAP RETURNS | H75: KG | I75: RMFR | J75: 208.3 | K75: 5838.22 | N75: -250 | O75: -7007.06 | P75: 1668.444 | Q75: 46763.49 | X75: 1626.744 | Y75: 45594.65 | Z75: =IFERROR((O75+Q75)/(N75+P75),Y75/X75) -> 28.028199
A76: 20200STR | B76: 44287 | C76: 44651 | D76: 20210401 | E76: 20220331 | F76: '0104086 | G76: EN 30 | H76: KG | I76: RMFR | P76: 60 | X76: 60 | Z76: =IFERROR((O76+Q76)/(N76+P76),Y76/X76) -> 0
A77: 20200STR | B77: 44287 | C77: 44651 | D77: 20210401 | E77: 20220331 | F77: '0104095 | G77: EN 43 B SCRAP RETURNS (C-45) | H77: KG | I77: RMFR | J77: 242 | K77: 8921.12 | N77: -11871.635 | O77: -491866.51 | P77: 23624.27 | Q77: 935858.98 | X77: 11994.635 | Y77: 452913.59 | Z77: =IFERROR((O77+Q77)/(N77+P77),Y77/X77) -> 37.778121
A78: 20200STR | B78: 44287 | C78: 44651 | D78: 20210401 | E78: 20220331 | F78: '0104100 | G78: EN-55 | H78: KG | I78: RMFR | J78: 852 | K78: 181845.75 | N78: -5876.898 | O78: -1153733.2 | P78: 5677.196 | Q78: 1085144.6 | X78: 652.298 | Y78: 113257.12 | Z78: =IFERROR((O78+Q78)/(N78+P78),Y78/X78) -> 343.4549
A79: 20200STR | B79: 44287 | C79: 44651 | D79: 20210401 | E79: 20220331 | F79: '0104102 | G79: IS10343 GR 4A | H79: KG | I79: RMFR | J79: 88 | K79: 2635.47 | N79: -18941.45 | O79: -575599.81 | P79: 46940 | Q79: 1487700.9 | X79: 28086.55 | Y79: 914736.58 | Z79: =IFERROR((O79+Q79)/(N79+P79),Y79/X79) -> 32.576727
A80: 20200STR | B80: 44287 | C80: 44651 | D80: 20210401 | E80: 20220331 | F80: '0104110 | G80: EN 354 SCRAP (28B4)IS10343GR3D | H80: KG | I80: RMFR | J80: 66262 | K80: 3772797.7 | N80: -399537.69 | O80: -22770681 | P80: 405950.03 | Q80: 23229984 | V80: 30034 | W80: 1742819 | X80: 102708.34 | Y80: 5974920 | Z80: =IFERROR((O80+Q80)/(N80+P80),Y80/X80) -> 71.628065
A81: 20200STR | B81: 44287 | C81: 44651 | D81: 20210401 | E81: 20220331 | F81: '0104116 | G81: 07-U-197 (DIN 1.4549) | H81: KG | I81: RMFR | J81: 48 | K81: 2852.16 | X81: 48 | Y81: 2852.16 | Z81: =IFERROR((O81+Q81)/(N81+P81),Y81/X81) -> 59.42
A82: 20200STR | B82: 44287 | C82: 44651 | D82: 20210401 | E82: 20220331 | F82: '0104118 | G82: DIN 1.7131 SCRAP | H82: KG | I82: RMFR | N82: -3535 | O82: -51558.7 | P82: 8056.5 | Q82: 117505.62 | X82: 4521.5 | Y82: 65946.92 | Z82: =IFERROR((O82+Q82)/(N82+P82),Y82/X82) -> 14.585186
A83: 20200STR | B83: 44287 | C83: 44651 | D83: 20210401 | E83: 20220331 | F83: '0104125 | G83: GUN METAL 85:5:5:5 | H83: KG | I83: RMFL | J83: 151.7 | K83: 20813.24 | P83: 7.8 | Q83: 1070.16 | R83: -159.5 | S83: -21883.4 | Z83: =IFERROR((O83+Q83)/(N83+P83),Y83/X83) -> 137.2
A84: 20200STR | B84: 44287 | C84: 44651 | D84: 20210401 | E84: 20220331 | F84: '0104129 | G84: HAST ALLOY C. | H84: KG | I84: RMFR | J84: 204 | K84: 204687.48 | P84: 2 | Q84: 2006.74 | R84: -206 | S84: -206694.22 | Z84: =IFERROR((O84+Q84)/(N84+P84),Y84/X84) -> 1003.37
A85: 20200STR | B85: 44287 | C85: 44651 | D85: 20210401 | E85: 20220331 | F85: '0104150 | G85: M.S.LOW CARBON | H85: KG | I85: RMFL | J85: 24290 | K85: 850851.08 | L85: 554419 | M85: 27562956 | N85: -578751.87 | O85: -28502050 | P85: 8989.041 | Q85: 444033.54 | X85: 8946.171 | Y85: 355790.39 | Z85: =IFERROR((O85+Q85)/(N85+P85),Y85/X85) -> 49.245081
A86: 20200STR | B86: 44287 | C86: 44651 | D86: 20210401 | E86: 20220331 | F86: '0104156 | G86: M-3 TOOL STEEL | H86: KG | I86: RMFR | J86: 216 | K86: 46425.17 | N86: -379.8 | O86: -81630.98 | P86: 235.82 | Q86: 50685.11 | X86: 72.02 | Y86: 15479.3 | Z86: =IFERROR((O86+Q86)/(N86+P86),Y86/X86) -> 214.93173
A87: 20200STR | B87: 44287 | C87: 44651 | D87: 20210401 | E87: 20220331 | F87: '0104160 | G87: NON MAGNETIC BAR STOCK | H87: KG | I87: RMFR | J87: 1392 | K87: 27299.16 | R87: -984 | S87: -19297.62 | X87: 408 | Y87: 8001.54 | Z87: =IFERROR((O87+Q87)/(N87+P87),Y87/X87) -> 19.611618
A88: 20200STR | B88: 44287 | C88: 44651 | D88: 20210401 | E88: 20220331 | F88: '0104162 | G88: NRI - 4970 | H88: KG | I88: RMFR | J88: 384 | K88: 151200 | R88: -384 | S88: -151200 | Z88: =IFERROR((O88+Q88)/(N88+P88),Y88/X88) -> #DIV/0!
A89: 20200STR | B89: 44287 | C89: 44651 | D89: 20210401 | E89: 20220331 | F89: '0104179 | G89: EN 56D | H89: KG | I89: RMFR | J89: 193 | K89: 14562.93 | N89: -300 | O89: -22636.74 | P89: 440 | Q89: 33200.54 | X89: 333 | Y89: 25126.73 | Z89: =IFERROR((O89+Q89)/(N89+P89),Y89/X89) -> 75.455714
A90: 20200STR | B90: 44287 | C90: 44651 | D90: 20210401 | E90: 20220331 | F90: '0104201 | G90: SILICON STEEL | H90: KG | I90: RMFR | P90: 18 | Q90: 1800 | X90: 18 | Y90: 1800 | Z90: =IFERROR((O90+Q90)/(N90+P90),Y90/X90) -> 100
A91: 20200STR | B91: 44287 | C91: 44651 | D91: 20210401 | E91: 20220331 | F91: '0104203 | G91: EN11 (14K37) | H91: KG | I91: RMFR | J91: 281 | K91: 8803.09 | N91: -935 | O91: -29291.5 | P91: 1112 | Q91: 35841.38 | X91: 458 | Y91: 15352.97 | Z91: =IFERROR((O91+Q91)/(N91+P91),Y91/X91) -> 37.004972
A92: 20200STR | B92: 44287 | C92: 44651 | D92: 20210401 | E92: 20220331 | F92: '0104212 | G92: STELLITE - 4 ( RETURNS ) | H92: KG | I92: RMFR | J92: 4.2 | K92: 9811.16 | X92: 4.2 | Y92: 9811.16 | Z92: =IFERROR((O92+Q92)/(N92+P92),Y92/X92) -> 2335.9905
A93: 20200STR | B93: 44287 | C93: 44651 | D93: 20210401 | E93: 20220331 | F93: '0104223 | G93: 24I4/5 TOOL STEEL | H93: KG | I93: RMFR | J93: 275.2 | K93: 27520 | X93: 275.2 | Y93: 27520 | Z93: =IFERROR((O93+Q93)/(N93+P93),Y93/X93) -> 100
A94: 20200STR | B94: 44287 | C94: 44651 | D94: 20210401 | E94: 20220331 | F94: '0104224 | G94: ASTM A732 Gr 7Q TY 164130 | H94: KG | I94: RMFR | P94: 37 | X94: 37 | Z94: =IFERROR((O94+Q94)/(N94+P94),Y94/X94) -> 0
A95: 20200STR | B95: 44287 | C95: 44651 | D95: 20210401 | E95: 20220331 | F95: '0104225 | G95: IS 10343 Gr.1Q (25N14) | H95: KG | I95: RMFR | J95: 216 | K95: 6964.61 | N95: -21288.5 | O95: -686510.3 | P95: 21267 | Q95: 685817.63 | X95: 194.5 | Y95: 6271.94 | Z95: =IFERROR((O95+Q95)/(N95+P95),Y95/X95) -> 32.217209
A96: 20200STR | B96: 44287 | C96: 44651 | D96: 20210401 | E96: 20220331 | F96: '0104257 | G96: 7U103(DIN 1.7242 16CR MO4)RETN | H96: KG | I96: RMFR | P96: 11 | X96: 11 | Z96: =IFERROR((O96+Q96)/(N96+P96),Y96/X96) -> 0
A97: 20200STR | B97: 44287 | C97: 44651 | D97: 20210401 | E97: 20220331 | F97: '0104258 | G97: 16 MN. CR. 5 | H97: KG | I97: RMFR | J97: 905 | K97: 32181.5 | N97: -41290.07 | O97: -1502309.1 | P97: 45216.29 | Q97: 1648564.7 | X97: 4831.22 | Y97: 178437.19 | Z97: =IFERROR((O97+Q97)/(N97+P97),Y97/X97) -> 37.251018
A98: 20200STR | B98: 44287 | C98: 44651 | D98: 20210401 | E98: 20220331 | F98: '0104260 | G98: 17-4 P.H. STEEL | H98: KG | I98: RMFR | J98: 712.4 | K98: 92170.31 | X98: 712.4 | Y98: 92170.31 | Z98: =IFERROR((O98+Q98)/(N98+P98),Y98/X98) -> 129.38
A99: 20200STR | B99: 44287 | C99: 44651 | D99: 20210401 | E99: 20220331 | F99: '0104266 | G99: 50 CR.V4 (OBSOLETE) | H99: KG | I99: RMFR | J99: 277 | K99: 10600.47 | X99: 277 | Y99: 10600.47 | Z99: =IFERROR((O99+Q99)/(N99+P99),Y99/X99) -> 38.268845
A100: 20200STR | B100: 44287 | C100: 44651 | D100: 20210401 | E100: 20220331 | F100: '0104269 | G100: 42 CR MO 4 [ 4W7 ] | H100: KG | I100: RMFR | J100: 90 | K100: 2694.81 | N100: -15 | O100: -449.13 | P100: 429.5 | Q100: 12860.21 | X100: 504.5 | Y100: 15105.89 | Z100: =IFERROR((O100+Q100)/(N100+P100),Y100/X100) -> 29.942292
A101: 20200STR | B101: 44287 | C101: 44651 | D101: 20210401 | E101: 20220331 | F101: '0104315 | G101: 25 CR MO 4 (7-U-301) | H101: KG | I101: RMFR | J101: 53 | P101: 834.232 | Q101: -0.74 | X101: 887.232 | Y101: -0.74 | Z101: =IFERROR((O101+Q101)/(N101+P101),Y101/X101) -> -0.00088704341
A102: 20200STR | B102: 44287 | C102: 44651 | D102: 20210401 | E102: 20220331 | F102: '0104326 | G102: ANC4B BS 3146 52-A-25 | H102: KG | I102: RMFR | J102: 2047 | K102: 322392.81 | X102: 2047 | Y102: 322392.81 | Z102: =IFERROR((O102+Q102)/(N102+P102),Y102/X102) -> 157.49527
A103: 20200STR | B103: 44287 | C103: 44651 | D103: 20210401 | E103: 20220331 | F103: '0104329 | G103: ANC2 BS 3146 P | H103: KG | I103: RMFR | J103: 1643.9 | K103: 130591.36 | N103: -20597.15 | O103: -1661883.8 | P103: 19891.33 | Q103: 1608690.3 | X103: 938.08 | Y103: 77397.83 | Z103: =IFERROR((O103+Q103)/(N103+P103),Y103/X103) -> 75.364158
A104: 20200STR | B104: 44287 | C104: 44651 | D104: 20210401 | E104: 20220331 | F104: '0104332 | G104: AISI 430 SCRAP (PURCHASE) | H104: KG | I104: RMFR | J104: 21.5 | K104: 949.75 | L104: 141620.3 | M104: 10202621 | N104: -132053.69 | O104: -9453248.9 | P104: 57 | Q104: 4026.48 | X104: 9645.11 | Y104: 754347.82 | Z104: =IFERROR((O104+Q104)/(N104+P104),Y104/X104) -> 71.586814
A105: 20200STR | B105: 44287 | C105: 44651 | D105: 20210401 | E105: 20220331 | F105: '0104336 | G105: ANC1 | H105: KG | I105: RMFR | J105: 382 | K105: 10592.86 | N105: -1438 | O105: -39875.74 | P105: 1676.5 | Q105: 46489.35 | X105: 620.5 | Y105: 17206.47 | Z105: =IFERROR((O105+Q105)/(N105+P105),Y105/X105) -> 27.730021
A106: 20200STR | B106: 44287 | C106: 44651 | D106: 20210401 | E106: 20220331 | F106: '0104339 | G106: M.S.SCRAP IN ASSORTED | H106: KG | I106: RMFL | J106: 5523 | K106: 154644 | N106: -5323 | O106: -149044 | X106: 200 | Y106: 5600 | Z106: =IFERROR((O106+Q106)/(N106+P106),Y106/X106) -> 28
A107: 20200STR | B107: 44287 | C107: 44651 | D107: 20210401 | E107: 20220331 | F107: '0104340 | G107: 1-Y-1 SCM-415 | H107: KG | I107: RMFR | J107: 1167 | K107: 37015.01 | P107: 11 | Q107: 348.9 | V107: -1178 | W107: -37363.45 | Y107: 0.46 | Z107: =IFERROR((O107+Q107)/(N107+P107),Y107/X107) -> 31.718182
A108: 20200STR | B108: 44287 | C108: 44651 | D108: 20210401 | E108: 20220331 | F108: '0104348 | G108: BS-3146 ANC 4-B | H108: KG | I108: RMFR | J108: 362 | K108: 67719.17 | N108: -4913.88 | O108: -892464.97 | P108: 4613.8 | Q108: 835592.63 | X108: 61.92 | Y108: 10846.83 | Z108: =IFERROR((O108+Q108)/(N108+P108),Y108/X108) -> 189.52393
...
